Workbook

Sheet Données Bruts
A1: N°Support | B1: N°Article | C1: Désignation | D1: Composition | E1: EAN | F1: EAN | G1: EAN | H1: Pays Origine | I1: Code Douane | J1: Colisage | K1: #Colis | L1: #Pces | M1: Poids Brut | N1: Poids Net | O1: Vol. Pce | P1: Vol.Total | Q1: PA Unitaire | R1: PA Global
A2: 18768943 | B2: 905236 | C2: HR Sabot injecté db chaud Fushia 36/41 | H2: CN | I2: 64029910 | J2: 1 | K2: 16 | L2: 16 | M2: 4.266 | N2: 3.84 | O2: 5.136 | P2: 82.176 | Q2: 3.68 | R2: 58.82
A3: 18768943 | B3: 997529 | C3: HR panty fant D formes | H3: CN | I3: 61152200 | J3: 5 | K3: 4 | L3: 20 | M3: 1.48 | N3: 1.332 | O3: 0.617 | P3: 12.34 | Q3: 1.86 | R3: 37.2
A4: 18768943 | B4: 991982 | C4: PR 0CM4 CO ULTRA RESIST TRANSP 20 D NOIR | H4: CN | I4: 61152200 | J4: 12 | K4: 3 | L4: 36 | M4: 1.86 | N4: 1.674 | O4: 0.633 | P4: 22.776 | Q4: 4.01 | R4: 144.36
A5: 18768943 | B5: 709775 | C5: HR panty Golden Lady liberté abs silhou | H5: IT | I5: 61152200 | J5: 12 | K5: 3 | L5: 36 | M5: 2.352 | N5: 2.117 | O5: 0.76 | P5: 27.36 | Q5: 3.71 | R5: 133.56
A6: 18768943 | B6: 793513 | C6: HR panty fant D POIS | H6: CN | I6: 61152100 | J6: 4 | K6: 4 | L6: 16 | M6: 1.14 | N6: 1.026 | O6: 0.781 | P6: 12.496 | Q6: 1.67 | R6: 26.64
A7: 18768943 | B7: 723185 | C7: HR Ultra fine Hebdo 4 paires 42/43 | E7: 3031446805734 | H7: BE | I7: 64069050 | J7: 3 | K7: 1 | L7: 3 | M7: 0.234 | N7: 0.211 | O7: 1 | P7: 3 | Q7: 2.71 | R7: 8.13
A8: 18768943 | B8: 996593 | C8: HR ULTRA FINE HEBDO 2 PAIRES 38/39 | E8: 3031446805765 | H8: BE | I8: 64069050 | J8: 3 | K8: 1 | L8: 3 | M8: 0.186 | N8: 0.167 | O8: 0.75 | P8: 2.25 | Q8: 1.39 | R8: 4.17
A9: 18768943 | B9: 929409 | C9: HR Protection froid 38/39 | E9: 3031446801743 | H9: BE | I9: 64069050 | J9: 3 | K9: 1 | L9: 3 | M9: 0.084 | N9: 0.076 | O9: 0.418 | P9: 1.254 | Q9: 2.11 | R9: 6.33
A10: 18768943 | B10: 723182 | C10: HR Ultra fine Hebdo 4 paires 40/41 | E10: 3031446805727 | H10: BE | I10: 64069050 | J10: 3 | K10: 1 | L10: 3 | M10: 0.219 | N10: 0.197 | O10: 1 | P10: 3 | Q10: 2.71 | R10: 8.13
A11: 18768943 | B11: 723168 | C11: HR Ultra fine Hebdo 4 paires 44/45 | E11: 3031446805741 | H11: BE | I11: 64069050 | J11: 3 | K11: 1 | L11: 3 | M11: 0.252 | N11: 0.227 | O11: 1 | P11: 3 | Q11: 2.71 | R11: 8.13
A12: 18768943 | B12: 996600 | C12: HR ULTRA FINE HEBDO 2 PAIRES 36/37 | E12: 3031446805758 | H12: BE | I12: 64069050 | J12: 3 | K12: 1 | L12: 3 | M12: 0.186 | N12: 0.167 | O12: 0.75 | P12: 2.25 | Q12: 1.39 | R12: 4.17
A13: 18768943 | B13: 763302 | C13: HR SS-GENE DB COTON BIO NOIR 40/46 | H13: ES | I13: 64041910 | J13: 2 | K13: 7 | L13: 14 | M13: 9.12 | N13: 8.208 | O13: 4.341 | P13: 60.774 | Q13: 4.55 | R13: 63.7
A14: 18768943 | B14: 763301 | C14: HR SS-GENE DB LAINE BIO NOIR 40/46 | H14: ES | I14: 64041910 | J14: 2 | K14: 6 | L14: 12 | M14: 7.872 | N14: 7.084 | O14: 4.135 | P14: 49.624 | Q14: 4.47 | R14: 53.66
A15: 18768943 | B15: 905233 | C15: HR Sabot injecté db chaud Marine 41/46 | H15: CN | I15: 64029910 | J15: 1 | K15: 16 | L15: 16 | M15: 5.637 | N15: 5.074 | O15: 6.918 | P15: 110.68 | Q15: 4.04 | R15: 64.62
A16: 18768943 | B16: 905234 | C16: HR Sabot injecté db chaud Noir 36/41 | H16: CN | I16: 64029910 | J16: 1 | K16: 12 | L16: 12 | M16: 3.21 | N16: 2.891 | O16: 5.036 | P16: 60.428 | Q16: 3.08 | R16: 36.96
A17: 18768943 | B17: 905231 | C17: HR Sabot injecté db chaud Noir 41/46 | H17: CN | I17: 64029910 | J17: 1 | K17: 16 | L17: 16 | M17: 5.496 | N17: 4.947 | O17: 6.902 | P17: 110.424 | Q17: 3.66 | R17: 58.51
A18: 18768943 | B18: 905235 | C18: HR Sabot injecté db chaud Gris 36/41 | H18: CN | I18: 64029910 | J18: 1 | K18: 12 | L18: 12 | M18: 3.226 | N18: 2.905 | O18: 5.198 | P18: 62.38 | Q18: 3.25 | R18: 38.94
A19: 18832507 | B19: 901451 | C19: BROCHURE D'ACCUEIL | H19: BE | I19: 48211010 | J19: 1 | K19: 5 | L19: 5 | M19: 0.15 | N19: 0.135 | O19: 0.157 | P19: 0.785 | Q19: 2 | R19: 10
A20: 18832507 | B20: 900850 | C20: EVERYDAY CREME A CAFE (CUPS) 20 X 10 GR | E20: 5400141167900 | H20: DE | I20: 4015011 | J20: 1 | K20: 5 | L20: 5 | M20: 1.145 | N20: 1.031 | O20: 0.746 | P20: 3.73 | Q20: 0.58 | R20: 2.9
A21: 18832507 | B21: 900216 | C21: B/100 FEUILLES ETIQUET. PALETTE POUBELLE | H21: BE | I21: 48219010 | J21: 1 | K21: 1 | L21: 1 | M21: 0.01 | N21: 0.009 | O21: 0.45 | P21: 0.45 | Q21: 11.02 | R21: 11.02
A22: 18832507 | B22: 900774 | C22: CARTON AMERICAIN | H22: FR | I22: 48191000 | J22: 10 | K22: 5 | L22: 50 | M22: 10 | N22: 9 | O22: 8.55 | P22: 427.5 | Q22: 2.58 | R22: 129
A23: 18832507 | B23: 901050 | C23: BONI ASSORTIMENT MELANGE 500GR | H23: BE | I23: 19053199 | J23: 1 | K23: 5 | L23: 5 | M23: 3.13 | N23: 2.817 | O23: 2.97 | P23: 14.85 | Q23: 2.85 | R23: 14.25
A24: 18832507 | B24: 900781 | C24: MAXI SACS | H24: FR | I24: 39232100 | J24: 25 | K24: 3 | L24: 75 | M24: 25.125 | N24: 22.613 | O24: 3 | P24: 225 | Q24: 1.22 | R24: 91.5
A25: 18832517 | B25: 915273 | C25: EDP 50ML. ORIENTAL | E25: 8715658440048 | H25: CN | I25: 33030010 | J25: 1 | K25: 2 | L25: 2 | M25: 2.424 | N25: 2.182 | O25: 4 | P25: 8 | Q25: 1.83 | R25: 3.66
A26: 18832517 | B26: 283973 | C26: BYPHASSE DISSOLVANT 250ML ESSENTIALS | E26: 8436097092703 | F26: 8437005723306 | G26: 8436097093984 | H26: ES | I26: 33043000 | J26: 1 | K26: 5 | L26: 5 | M26: 1.335 | N26: 1.202 | O26: 0.507 | P26: 2.535 | Q26: 0.69 | R26: 3.45
A27: 18832651 | B27: 700322 | C27: PR JEANS REGULAR FIT DENIM NOIR | H27: BD | I27: 62046390 | J27: 1 | K27: 1 | L27: 1 | M27: 0.471 | N27: 0.424 | O27: 2.533 | P27: 2.533 | Q27: 7.47 | R27: 7.47
A28: 18832651 | B28: 991150 | C28: PR CEINT DGT NOIR Silver | H28: CN | I28: 39262000 | J28: 2 | K28: 1 | L28: 2 | M28: 0.244 | N28: 0.22 | O28: 0.442 | P28: 0.884 | Q28: 1.05 | R28: 2.1
A29: 18832651 | B29: 659963 | C29: PR PANT DROIT STRETCH GRIS | H29: BD | I29: 62046290 | J29: 1 | K29: 1 | L29: 1 | M29: 0.497 | N29: 0.447 | O29: 3 | P29: 3 | Q29: 7.93 | R29: 7.93
A30: 18832651 | B30: 635597 | C30: PR LEGGING LONG NOIR | H30: IN | I30: 61152900 | J30: 2 | K30: 1 | L30: 2 | M30: 0.334 | N30: 0.301 | O30: 1.386 | P30: 2.772 | Q30: 2.58 | R30: 5.16
A31: 18832651 | B31: 942303 | C31: HR LEGGING DARK GREY MEL | H31: IN | I31: 61142000 | J31: 2 | K31: 1 | L31: 2 | M31: 0.352 | N31: 0.317 | O31: 1.176 | P31: 2.352 | Q31: 2.55 | R31: 5.1
A32: 18832651 | B32: 700245 | C32: HR Cardigan Polar ftte turquoise | H32: BD | I32: 61109090 | J32: 1 | K32: 1 | L32: 1 | M32: 0.136 | N32: 0.122 | O32: 1.8 | P32: 1.8 | Q32: 2.86 | R32: 2.86
A33: 18832651 | B33: 700243 | C33: HR Cardigan Polar ftte bleu nuit | H33: BD | I33: 61109090 | J33: 1 | K33: 1 | L33: 1 | M33: 0.204 | N33: 0.184 | O33: 2.4 | P33: 2.4 | Q33: 2.93 | R33: 2.93
A34: 18832651 | B34: 700247 | C34: HR Cardigan Polar fille rose | H34: BD | I34: 61109090 | J34: 1 | K34: 1 | L34: 1 | M34: 0.333 | N34: 0.3 | O34: 2.666 | P34: 2.666 | Q34: 3.6 | R34: 3.6
A35: 18832651 | B35: 380893 | C35: PR tshirt fines brides cot-ea noir | H35: IN | I35: 61091000 | J35: 2 | K35: 1 | L35: 2 | M35: 0.224 | N35: 0.202 | O35: 1.2 | P35: 2.4 | Q35: 1.03 | R35: 2.06
A36: 18832651 | B36: 991151 | C36: PR CEINT DGT CAMEL Gold | H36: CN | I36: 39262000 | J36: 2 | K36: 1 | L36: 2 | M36: 0.24 | N36: 0.216 | O36: 0.442 | P36: 0.884 | Q36: 1.05 | R36: 2.1
A37: 18832651 | B37: 745081 | C37: PR CARDIGAN MOLLETON VIEUX ROSE | H37: PK | I37: 61101990 | J37: 2 | K37: 1 | L37: 2 | M37: 0.86 | N37: 0.774 | O37: 3.52 | P37: 7.04 | Q37: 4.77 | R37: 9.54
A38: 18832651 | B38: 380904 | C38: HR Polar cintré full zip NOIR | H38: CN | I38: 61103010 | J38: 1 | K38: 1 | L38: 1 | M38: 0.35 | N38: 0.315 | O38: 3.3 | P38: 3.3 | Q38: 5.6 | R38: 5.6
... A58: 18832651 | B58: 707862 | C58: HR Collant micro Fille LiLi Marine | H58: PL | I58: 61152100 | J58: 3 | K58: 1 | L58: 3 | M58: 0.129 | N58: 0.116 | O58: 0.455 | P58: 1.365 | Q58: 0.87 | R58: 2.61
A59: 18832651 | B59: 991176 | C59: PT lot 3 culottes Frozen | E59: 8720193921013 | H59: CN | I59: 61082100 | J59: 12 | K59: 1 | L59: 12 | M59: 0.852 | N59: 0.767 | O59: 0.585 | P59: 7.02 | Q59: 1.78 | R59: 21.36
A60: 18832651 | B60: 613275 | C60: PR V10 Brassière large bret noir | H60: CN | I60: 61089200 | J60: 2 | K60: 1 | L60: 2 | M60: 0.172 | N60: 0.155 | O60: 0.771 | P60: 1.542 | Q60: 1.4 | R60: 2.8
A61: 18832651 | B61: 613302 | C61: PR V10 Culotte dentelle ss cout noir | H61: CN | I61: 61089200 | J61: 2 | K61: 1 | L61: 2 | M61: 0.144 | N61: 0.13 | O61: 0.472 | P61: 0.944 | Q61: 1.37 | R61: 2.74
A62: 18832651 | B62: 664022 | C62: PR Collant microfibre 60D Noir | H62: PL | I62: 61152200 | J62: 4 | K62: 1 | L62: 4 | M62: 0.3 | N62: 0.27 | O62: 0.541 | P62: 2.164 | Q62: 1.22 | R62: 4.88
A63: 18832651 | B63: 913369 | C63: PR Collant massage mimat mo, NATURAL, XL | E63: 2090001191348 | H63: PL | I63: 61152100 | J63: 4 | K63: 1 | L63: 4 | M63: 0.34 | N63: 0.306 | O63: 0.84 | P63: 3.36 | Q63: 1.27 | R63: 5.08
A64: 18832651 | B64: 663985 | C64: PR Collant lycra satiné 20D Noir | H64: PL | I64: 61152100 | J64: 4 | K64: 1 | L64: 4 | M64: 0.24 | N64: 0.216 | O64: 0.574 | P64: 2.296 | Q64: 0.93 | R64: 3.72
A65: 18832651 | B65: 684517 | C65: PR String lazer cut chair PA/EA | H65: CN | I65: 61082200 | J65: 1 | K65: 3 | L65: 3 | M65: 0.083 | N65: 0.074 | O65: 0.342 | P65: 1.026 | Q65: 1.19 | R65: 3.57
A66: 18832651 | B66: 638821 | C66: PR Gaine dame ventre plat noir | H66: CN | I66: 61082100 | J66: 1 | K66: 1 | L66: 1 | M66: 0.103 | N66: 0.093 | O66: 1.006 | P66: 1.006 | Q66: 2.18 | R66: 2.18
A67: 18832651 | B67: 663875 | C67: PR Lot 5 mi-bas voile chif 20D Beige | E67: 2090000943962 | H67: CN | I67: 61153090 | J67: 4 | K67: 1 | L67: 4 | M67: 0.248 | N67: 0.223 | O67: 0.496 | P67: 1.984 | Q67: 1.17 | R67: 4.68
A68: 18832651 | B68: 664011 | C68: PR Collant Lycra mat antimaille fil Noir | H68: CN | I68: 61152100 | J68: 4 | K68: 1 | L68: 4 | M68: 0.248 | N68: 0.223 | O68: 0.426 | P68: 1.704 | Q68: 1.4 | R68: 5.6
A69: 18832651 | B69: 380510 | C69: PT Lot 2 culottes D noirs DISCRET | H69: CN | I69: 61082100 | J69: 4 | K69: 1 | L69: 4 | M69: 0.484 | N69: 0.436 | O69: 0.84 | P69: 3.36 | Q69: 1.96 | R69: 7.84
A70: 18832651 | B70: 361405 | C70: PT lot 2 slips noir | H70: CN | I70: 61082100 | J70: 1 | K70: 3 | L70: 3 | M70: 0.168 | N70: 0.151 | O70: 0.417 | P70: 1.251 | Q70: 0.79 | R70: 2.37
A71: 18832651 | B71: 987061 | C71: PR Brassière large bretelle PRUNE MALAGA | H71: CN | I71: 62121010 | J71: 2 | K71: 1 | L71: 2 | M71: 0.174 | N71: 0.157 | O71: 0.588 | P71: 1.176 | Q71: 1.74 | R71: 3.48
A72: 18832651 | B72: 603405 | C72: PR Lot 2 SG white / Black micro + dent | H72: CN | I72: 62121090 | J72: 1 | K72: 1 | L72: 1 | M72: 0.295 | N72: 0.266 | O72: 2.97 | P72: 2.97 | Q72: 5.8 | R72: 5.8
A73: 18832651 | B73: 986959 | C73: HR 70564 SG A/A ARUM VERT OMBRE | H73: CN | I73: 62121090 | J73: 1 | K73: 1 | L73: 1 | M73: 0.103 | N73: 0.093 | O73: 1.533 | P73: 1.533 | Q73: 11.76 | R73: 11.76
A74: 18832651 | B74: 755783 | C74: PR Brassière large bret gris chiné | H74: CN | I74: 61089200 | J74: 2 | K74: 1 | L74: 2 | M74: 0.146 | N74: 0.131 | O74: 0.554 | P74: 1.108 | Q74: 1.54 | R74: 3.08
A75: 18832651 | B75: 707645 | C75: PT lot 3 tennis terry Fila blanc | H75: PT | I75: 61159500 | J75: 4 | K75: 1 | L75: 4 | M75: 0.868 | N75: 0.781 | O75: 1.84 | P75: 7.36 | Q75: 2.4 | R75: 9.6
A76: 18832651 | B76: 725821 | C76: PR PYJASHORT JERSEY NAVY | H76: BD | I76: 61031090 | J76: 1 | K76: 1 | L76: 1 | M76: 0.358 | N76: 0.322 | O76: 1.642 | P76: 1.642 | Q76: 4.26 | R76: 4.26
A77: 18832651 | B77: 750120 | C77: PR SC ceinture PU brun 3cm | E77: 2090001128054 | H77: CN | I77: 61091000 | J77: 5 | K77: 1 | L77: 5 | M77: 0.635 | N77: 0.572 | O77: 0.5 | P77: 2.5 | Q77: 1.1 | R77: 5.5
A78: 18832651 | B78: 659967 | C78: PR PANT DROIT STRETCH NOIR | H78: BD | I78: 62046290 | J78: 1 | K78: 2 | L78: 2 | M78: 1.243 | N78: 1.119 | O78: 2.75 | P78: 5.5 | Q78: 7.4 | R78: 14.8
A79: 18832651 | B79: 655050 | C79: HR POLAR FULL ZIP MAUVE | H79: BD | I79: 61109090 | J79: 2 | K79: 2 | L79: 4 | M79: 1.91 | N79: 1.719 | O79: 5.166 | P79: 20.664 | Q79: 5.46 | R79: 21.84
A80: 18832651 | B80: 727156 | C80: PT Lot 5 cho7 PB | H80: CN | I80: 61159500 | J80: 4 | K80: 1 | L80: 4 | M80: 0.7 | N80: 0.63 | O80: 0.772 | P80: 3.088 | Q80: 1.26 | R80: 5.04
A81: 18832651 | B81: 743935 | C81: HT collant BB écru | H81: CN | I81: 61152900 | J81: 1 | K81: 2 | L81: 2 | M81: 0.108 | N81: 0.097 | O81: 0.304 | P81: 0.608 | Q81: 0.96 | R81: 1.92
A82: 18832651 | B82: 606328 | C82: PR Lot 2 boxers désaiguillés N+B PA/EA | H82: CN | I82: 61082200 | J82: 1 | K82: 1 | L82: 1 | M82: 0.086 | N82: 0.077 | O82: 0.489 | P82: 0.489 | Q82: 2.88 | R82: 2.88
A83: 18832651 | B83: 692488 | C83: PR Collant lycra semi-glossy 15 NOIR XXL | E83: 2090001004433 | H83: BE | I83: 61152100 | J83: 4 | K83: 1 | L83: 4 | M83: 0.252 | N83: 0.227 | O83: 0.638 | P83: 2.552 | Q83: 0.82 | R83: 3.28
A84: 18832651 | B84: 725798 | C84: PR PYJASHORT JERSEY BORDEAUX | H84: BD | I84: 61031090 | J84: 1 | K84: 1 | L84: 1 | M84: 0.316 | N84: 0.284 | O84: 1.642 | P84: 1.642 | Q84: 4.21 | R84: 4.21
A85: 18832651 | B85: 600227 | C85: PT lot 3 tennis Puma homme | H85: NL | I85: 61159500 | J85: 1 | K85: 3 | L85: 3 | M85: 0.692 | N85: 0.623 | O85: 1.533 | P85: 4.6 | Q85: 3.5 | R85: 10.5
A86: 18832651 | B86: 752671 | C86: HT lot 2 heat socks viscose | E86: 2090001134116 | H86: CN | I86: 61152100 | J86: 5 | K86: 1 | L86: 5 | M86: 1.325 | N86: 1.193 | O86: 2.136 | P86: 10.68 | Q86: 2.13 | R86: 10.65
A87: 18832651 | B87: 683902 | C87: PT Lot 2 slips gris chiné CO | H87: CN | I87: 61071100 | J87: 1 | K87: 3 | L87: 3 | M87: 0.552 | N87: 0.497 | O87: 1.344 | P87: 4.032 | Q87: 1.88 | R87: 5.64
A88: 18832651 | B88: 663873 | C88: PR Lot 2 mibas mous+bord confor 20D Auba | E88: 2090000943955 | H88: PL | I88: 61153011 | J88: 4 | K88: 1 | L88: 4 | M88: 0.132 | N88: 0.119 | O88: 0.276 | P88: 1.104 | Q88: 0.64 | R88: 2.56
A89: 18832651 | B89: 663864 | C89: PR Lot 2 socq voile repass 20D Noir | E89: 2090000943863 | H89: PL | I89: 61153019 | J89: 4 | K89: 1 | L89: 4 | M89: 0.108 | N89: 0.097 | O89: 0.345 | P89: 1.38 | Q89: 0.81 | R89: 3.24
A90: 18832651 | B90: 659181 | C90: HR lot 2 cho7 Slazenger High Performance | E90: 2090000925111 | H90: CN | I90: 61159500 | J90: 10 | K90: 1 | L90: 10 | M90: 1.52 | N90: 1.368 | O90: 1.5 | P90: 15 | Q90: 1.88 | R90: 18.8
A91: 18832651 | B91: 725822 | C91: PR PYJASHORT WOVEN GRIS | H91: PK | I91: 61032200 | J91: 1 | K91: 2 | L91: 2 | M91: 0.72 | N91: 0.648 | O91: 3.2 | P91: 6.4 | Q91: 4.21 | R91: 8.42
A92: 18832916 | B92: 1020700 | C92: BOITE PAIN PS+BAM FRESHEAT | E92: 3560237583907 | H92: CN | I92: 44191900 | J92: 1 | K92: 1 | L92: 1 | M92: 0.865 | N92: 0.779 | O92: 11.22 | P92: 11.22 | Q92: 5.08 | R92: 5.08
A93: 18832916 | B93: 682224 | C93: BOITE A CLIPS RECT. 1,6L | E93: 2090000979121 | H93: CN | I93: 39241000 | J93: 1 | K93: 2 | L93: 2 | M93: 0.54 | N93: 0.486 | O93: 3.263 | P93: 6.526 | Q93: 2.11 | R93: 4.22
A94: 18832916 | B94: 949306 | C94: LUNCHBOX 3EN1 Rose | E94: 5410801113000 | H94: BE | I94: 39241000 | J94: 1 | K94: 3 | L94: 3 | M94: 0.84 | N94: 0.756 | O94: 3.645 | P94: 10.935 | Q94: 3.7 | R94: 11.1
A95: 18832916 | B95: 1001570 | C95: SUPPORT ESS-TOUT FIL H30CM | E95: 3664944388197 | H95: CN | I95: 73239900 | J95: 1 | K95: 2 | L95: 2 | M95: 0.504 | N95: 0.454 | O95: 1.249 | P95: 2.498 | Q95: 1.37 | R95: 2.74
A96: 18832916 | B96: 708113 | C96: BICARBONATE DE SOUDE 1 KG FOREVER | E96: 5400191808723 | H96: BE | I96: 28363000 | J96: 1 | K96: 3 | L96: 3 | M96: 3.318 | N96: 2.986 | O96: 2.057 | P96: 6.171 | Q96: 3.35 | R96: 10.05
A97: 18832916 | B97: 986642 | C97: EPONGE VEG GRAT TOU SURF X3 | E97: 5410721515168 | H97: FR | I97: 68053000 | J97: 16 | K97: 1 | L97: 16 | M97: 1.12 | N97: 1.008 | O97: 0.587 | P97: 9.392 | Q97: 0.63 | R97: 10.08
A98: 18832916 | B98: 746305 | C98: LAVETTE MF COLORS X 8 | E98: 4023103185975 | H98: CN | I98: 63071010 | J98: 1 | K98: 3 | L98: 3 | M98: 0.732 | N98: 0.659 | O98: 2.016 | P98: 6.048 | Q98: 4.65 | R98: 13.95
A99: 18832916 | B99: 772930 | C99: GEL WC DETARTRANT ECOLOGIQUE | E99: 3563210022288 | H99: FR | I99: 34025090 | J99: 1 | K99: 2 | L99: 2 | M99: 1.74 | N99: 1.566 | O99: 1.666 | P99: 3.332 | Q99: 2.54 | R99: 5.08
A100: 18832916 | B100: 302565 | C100: 2 EPONGES A RECURER VEGETALES BLEU | E100: 8710648172022 | H100: NL | I100: 48030090 | J100: 1 | K100: 6 | L100: 6 | M100: 0.33 | N100: 0.297 | O100: 0.545 | P100: 3.27 | Q100: 0.59 | R100: 3.54
A101: 18832916 | B101: 624895 | C101: Savon d'Alep vrac 1kg | E101: 3593290025718 | H101: SY | I101: 34011900 | J101: 1 | K101: 2 | L101: 2 | M101: 2.306 | N101: 2.075 | O101: 4.333 | P101: 8.666 | Q101: 10.02 | R101: 20.04
A102: 18832916 | B102: 342217 | C102: BICARBONATE DE SOUDE 500G | E102: 5400191806583 | H102: BE | I102: 28363000 | J102: 6 | K102: 1 | L102: 6 | M102: 3.438 | N102: 3.094 | O102: 0.891 | P102: 5.346 | Q102: 1.87 | R102: 11.22
A103: 18832916 | B103: 944588 | C103: CARAFE 1L MISURA VER | E103: 11381000626 | F103: 8001133841708 | H103: IT | I103: 70134999 | J103: 1 | K103: 5 | L103: 5 | M103: 4.25 | N103: 3.825 | O103: 4.375 | P103: 21.875 | Q103: 1.99 | R103: 9.95
A104: 18832916 | B104: 943166 | C104: 2 VERRES A MARTINI 26CL | E104: 3491955565008 | H104: NL | I104: 70132890 | J104: 1 | K104: 1 | L104: 1 | M104: 0.39 | N104: 0.351 | O104: 6.183 | P104: 6.183 | Q104: 2.38 | R104: 2.38
A105: 18832916 | B105: 955600 | C105: DIAMOND GOBELET 30CL OCEAN BLUE | E105: 8004360065022 | H105: IT | I105: 70133799 | J105: 6 | K105: 2 | L105: 12 | M105: 3.996 | N105: 3.596 | O105: 0.736 | P105: 8.832 | Q105: 1.04 | R105: 12.48
A106: 18832916 | B106: 919303 | C106: PASSE LEGUMES EN INOX DIA.24CM | E106: 8032797730299 | H106: IT | I106: 82100000 | J106: 1 | K106: 1 | L106: 1 | M106: 0.803 | N106: 0.723 | O106: 10.5 | P106: 10.5 | Q106: 11.16 | R106: 11.16
A107: 18832916 | B107: 743974 | C107: PRESSE PUREE PLIANT 29 CM INOX/PP | E107: 3560238519424 | H107: CN | I107: 39241000 | J107: 1 | K107: 6 | L107: 6 | M107: 1.278 | N107: 1.15 | O107: 1.529 | P107: 9.174 | Q107: 2.03 | R107: 12.18
A108: 18832916 | B108: 915281 | C108: TIRE BOUCHON ALPINA PP/CHROME | E108: 8711252170251 | H108: CN | I108: 39241000 | J108: 1 | K108: 9 | L108: 9 | M108: 0.882 | N108: 0.794 | O108: 0.532 | P108: 4.788 | Q108: 1.17 | R108: 10.53
A109: 18832916 | B109: 383537 | C109: POELE CERAM 24C TOUS FEUX+INDUCTION | E109: 2090000694062 | H109: CN | I109: 76151080 | J109: 3 | K109: 1 | L109: 3 | M109: 2.538 | N109: 2.284 | O109: 6.02 | P109: 18.06 | Q109: 5.42 | R109: 16.26
A110: 18832916 | B110: 1021417 | C110: Tough poêle 28 cm TEFAL | E110: 3168430344037 | H110: FR | I110: 76151080 | J110: 1 | K110: 2 | L110: 2 | M110: 2.772 | N110: 2.495 | O110: 9.25 | P110: 18.5 | Q110: 21.47 | R110: 42.94
A111: 18832916 | B111: 609054 | C111: MOULE DEMONTABLE ROND 26CM | E111: 3560239397731 | H111: CN | I111: 73239900 | J111: 1 | K111: 3 | L111: 3 | M111: 1.608 | N111: 1.447 | O111: 7.02 | P111: 21.06 | Q111: 2.65 | R111: 7.95
A112: 18832916 | B112: 372328 | C112: S6 CUILLERES CAFE ANDREA INOX MAESTRO | E112: 2090000642827 | H112: CN | I112: 82152010 | J112: 10 | K112: 1 | L112: 10 | M112: 1.49 | N112: 1.341 | O112: 0.184 | P112: 1.84 | Q112: 1.3 | R112: 13
A113: 18832916 | B113: 716998 | C113: SET DE TABLE WOVEN GRIS | E113: 3491955115005 | H113: CN | I113: 39241000 | J113: 12 | K113: 1 | L113: 12 | M113: 0.936 | N113: 0.842 | O113: 0.156 | P113: 1.872 | Q113: 0.53 | R113: 6.36
A114: 18832916 | B114: 969231 | C114: Bouteille isolante 1L avec silicone- 3 a | E114: 5400370127379 | H114: CN | I114: 96170000 | J114: 1 | K114: 3 | L114: 3 | M114: 1.749 | N114: 1.574 | O114: 3.217 | P114: 9.651 | Q114: 6.48 | R114: 19.44
A115: 18832916 | B115: 905014 | C115: GOURDE PLASTIQUE LOL 400ML | E115: 8412497168323 | H115: CN | I115: 39233010 | J115: 1 | K115: 3 | L115: 3 | M115: 0.225 | N115: 0.203 | O115: 1.127 | P115: 3.381 | Q115: 1.03 | R115: 3.09
... A126: 18832916 | B126: 943007 | C126: PICHET AVEC ANSE 1.1L | E126: 8001691575008 | H126: IT | I126: 70134999 | J126: 1 | K126: 5 | L126: 5 | M126: 3.765 | N126: 3.389 | O126: 2.618 | P126: 13.09 | Q126: 2.74 | R126: 13.7
A127: 18832916 | B127: 791844 | C127: 100 Assiet.carton 23cm Blanc | E127: 3353890795066 | F127: 3491953961666 | H127: FR | I127: 48236910 | J127: 1 | K127: 5 | L127: 5 | M127: 4.9 | N127: 4.41 | O127: 3.571 | P127: 17.855 | Q127: 2.02 | R127: 10.1
A128: 18832916 | B128: 949963 | C128: MUG MICRO-ONDES PAW PATROL | E128: 8412497189045 | H128: CN | I128: 39241000 | J128: 1 | K128: 2 | L128: 2 | M128: 0.15 | N128: 0.135 | O128: 0.855 | P128: 1.71 | Q128: 1.22 | R128: 2.44
A129: 18832916 | B129: 983320 | C129: POKEMON LUNCHBOX | E129: 8412497080748 | H129: CN | I129: 39241000 | J129: 1 | K129: 2 | L129: 2 | M129: 0.226 | N129: 0.203 | O129: 1.805 | P129: 3.61 | Q129: 1.28 | R129: 2.56
...

Sheet Combiner
A1: N°Support | B1: N°Article | C1: Désignation | D1: Composition | E1: EAN | F1: EAN | G1: EAN | H1: Conca Valeur | I1: Colisage | J1: #Colis | K1: #Pces | L1: Poids Brut | M1: Poids Net | N1: Vol. Pce | O1: Vol.Total | P1: PA Unitaire | Q1: PA Global
A2: 18768943 | B2: 905236 | C2: HR Sabot injecté db chaud Fushia 36/41 | H2: CN64029910 | I2: 1 | J2: 16 | K2: 16 | L2: 4.266 | M2: 3.84 | N2: 5.136 | O2: 82.176 | P2: 3.68 | Q2: 58.82
A3: 18768943 | B3: 997529 | C3: HR panty fant D formes | H3: CN61152200 | I3: 5 | J3: 4 | K3: 20 | L3: 1.48 | M3: 1.332 | N3: 0.617 | O3: 12.34 | P3: 1.86 | Q3: 37.2 | T3: Colisage | U3: #Colis | V3: #Pces | W3: Poids Brut | X3: Poids Net | Y3: Vol. Pce | Z3: Vol.Total | AA3: PA Unitaire | AB3: PA Global
A4: 18768943 | B4: 991982 | C4: PR 0CM4 CO ULTRA RESIST TRANSP 20 D NOIR | H4: CN61152200 | I4: 12 | J4: 3 | K4: 36 | L4: 1.86 | M4: 1.674 | N4: 0.633 | O4: 22.776 | P4: 4.01 | Q4: 144.36 | S4: CN64029910 | T4: 17 | U4: 74 | V4: 84 | W4: 28.927 | X4: 26.039 | Y4: 39.81 | Z4: 489.808 | AA4: 38.65 | AB4: 383.49
A5: 18768943 | B5: 709775 | C5: HR panty Golden Lady liberté abs silhou | H5: IT61152200 | I5: 12 | J5: 3 | K5: 36 | L5: 2.352 | M5: 2.117 | N5: 0.76 | O5: 27.36 | P5: 3.71 | Q5: 133.56 | S5: CN61152200 | T5: 17 | U5: 7 | V5: 56 | W5: 3.34 | X5: 3.006 | Y5: 1.25 | Z5: 35.116 | AA5: 5.87 | AB5: 181.56
A6: 18768943 | B6: 793513 | C6: HR panty fant D POIS | H6: CN61152100 | I6: 4 | J6: 4 | K6: 16 | L6: 1.14 | M6: 1.026 | N6: 0.781 | O6: 12.496 | P6: 1.67 | Q6: 26.64 | S6: IT61152200 | T6: 12 | U6: 3 | V6: 36 | W6: 2.352 | X6: 2.117 | Y6: 0.76 | Z6: 27.36 | AA6: 3.71 | AB6: 133.56
A7: 18768943 | B7: 723185 | C7: HR Ultra fine Hebdo 4 paires 42/43 | E7: 3031446805734 | H7: BE64069050 | I7: 3 | J7: 1 | K7: 3 | L7: 0.234 | M7: 0.211 | N7: 1 | O7: 3 | P7: 2.71 | Q7: 8.13 | S7: CN61152100 | T7: 13 | U7: 6 | V7: 25 | W7: 2.713 | X7: 2.442 | Y7: 3.343 | Z7: 24.88 | AA7: 5.2 | AB7: 42.89
A8: 18768943 | B8: 996593 | C8: HR ULTRA FINE HEBDO 2 PAIRES 38/39 | E8: 3031446805765 | H8: BE64069050 | I8: 3 | J8: 1 | K8: 3 | L8: 0.186 | M8: 0.167 | N8: 0.75 | O8: 2.25 | P8: 1.39 | Q8: 4.17 | S8: BE64069050 | T8: 18 | U8: 6 | V8: 18 | W8: 1.161 | X8: 1.045 | Y8: 4.918 | Z8: 14.754 | AA8: 13.02 | AB8: 39.06
A9: 18768943 | B9: 929409 | C9: HR Protection froid 38/39 | E9: 3031446801743 | H9: BE64069050 | I9: 3 | J9: 1 | K9: 3 | L9: 0.084 | M9: 0.076 | N9: 0.418 | O9: 1.254 | P9: 2.11 | Q9: 6.33 | S9: ES64041910 | T9: 5 | U9: 14 | V9: 27 | W9: 17.587 | X9: 15.828 | Y9: 12.817 | Z9: 114.739 | AA9: 12.22 | AB9: 120.56
A10: 18768943 | B10: 723182 | C10: HR Ultra fine Hebdo 4 paires 40/41 | E10: 3031446805727 | H10: BE64069050 | I10: 3 | J10: 1 | K10: 3 | L10: 0.219 | M10: 0.197 | N10: 1 | O10: 3 | P10: 2.71 | Q10: 8.13 | S10: BE48211010 | T10: 1 | U10: 5 | V10: 5 | W10: 0.15 | X10: 0.135 | Y10: 0.157 | Z10: 0.785 | AA10: 2 | AB10: 10
A11: 18768943 | B11: 723168 | C11: HR Ultra fine Hebdo 4 paires 44/45 | E11: 3031446805741 | H11: BE64069050 | I11: 3 | J11: 1 | K11: 3 | L11: 0.252 | M11: 0.227 | N11: 1 | O11: 3 | P11: 2.71 | Q11: 8.13 | S11: DE04015011 | T11: 1 | U11: 5 | V11: 5 | W11: 1.145 | X11: 1.031 | Y11: 0.746 | Z11: 3.73 | AA11: 0.58 | AB11: 2.9
A12: 18768943 | B12: 996600 | C12: HR ULTRA FINE HEBDO 2 PAIRES 36/37 | E12: 3031446805758 | H12: BE64069050 | I12: 3 | J12: 1 | K12: 3 | L12: 0.186 | M12: 0.167 | N12: 0.75 | O12: 2.25 | P12: 1.39 | Q12: 4.17 | S12: BE48219010 | T12: 1 | U12: 1 | V12: 1 | W12: 0.01 | X12: 0.009 | Y12: 0.45 | Z12: 0.45 | AA12: 11.02 | AB12: 11.02
A13: 18768943 | B13: 763302 | C13: HR SS-GENE DB COTON BIO NOIR 40/46 | H13: ES64041910 | I13: 2 | J13: 7 | K13: 14 | L13: 9.12 | M13: 8.208 | N13: 4.341 | O13: 60.774 | P13: 4.55 | Q13: 63.7 | S13: FR48191000 | T13: 10 | U13: 5 | V13: 50 | W13: 10 | X13: 9 | Y13: 8.55 | Z13: 427.5 | AA13: 2.58 | AB13: 129
A14: 18768943 | B14: 763301 | C14: HR SS-GENE DB LAINE BIO NOIR 40/46 | H14: ES64041910 | I14: 2 | J14: 6 | K14: 12 | L14: 7.872 | M14: 7.084 | N14: 4.135 | O14: 49.624 | P14: 4.47 | Q14: 53.66 | S14: BE19053199 | T14: 1 | U14: 5 | V14: 5 | W14: 3.13 | X14: 2.817 | Y14: 2.97 | Z14: 14.85 | AA14: 2.85 | AB14: 14.25
A15: 18768943 | B15: 905233 | C15: HR Sabot injecté db chaud Marine 41/46 | H15: CN64029910 | I15: 1 | J15: 16 | K15: 16 | L15: 5.637 | M15: 5.074 | N15: 6.918 | O15: 110.68 | P15: 4.04 | Q15: 64.62 | S15: FR39232100 | T15: 25 | U15: 3 | V15: 75 | W15: 25.125 | X15: 22.613 | Y15: 3 | Z15: 225 | AA15: 1.22 | AB15: 91.5
A16: 18768943 | B16: 905234 | C16: HR Sabot injecté db chaud Noir 36/41 | H16: CN64029910 | I16: 1 | J16: 12 | K16: 12 | L16: 3.21 | M16: 2.891 | N16: 5.036 | O16: 60.428 | P16: 3.08 | Q16: 36.96 | S16: CN33030010 | T16: 1 | U16: 2 | V16: 2 | W16: 2.424 | X16: 2.182 | Y16: 4 | Z16: 8 | AA16: 1.83 | AB16: 3.66
A17: 18768943 | B17: 905231 | C17: HR Sabot injecté db chaud Noir 41/46 | H17: CN64029910 | I17: 1 | J17: 16 | K17: 16 | L17: 5.496 | M17: 4.947 | N17: 6.902 | O17: 110.424 | P17: 3.66 | Q17: 58.51 | S17: ES33043000 | T17: 1 | U17: 5 | V17: 5 | W17: 1.335 | X17: 1.202 | Y17: 0.507 | Z17: 2.535 | AA17: 0.69 | AB17: 3.45
A18: 18768943 | B18: 905235 | C18: HR Sabot injecté db chaud Gris 36/41 | H18: CN64029910 | I18: 1 | J18: 12 | K18: 12 | L18: 3.226 | M18: 2.905 | N18: 5.198 | O18: 62.38 | P18: 3.25 | Q18: 38.94 | S18: BD62046390 | T18: 1 | U18: 1 | V18: 1 | W18: 0.471 | X18: 0.424 | Y18: 2.533 | Z18: 2.533 | AA18: 7.47 | AB18: 7.47
A19: 18832507 | B19: 901451 | C19: BROCHURE D'ACCUEIL | H19: BE48211010 | I19: 1 | J19: 5 | K19: 5 | L19: 0.15 | M19: 0.135 | N19: 0.157 | O19: 0.785 | P19: 2 | Q19: 10 | S19: CN39262000 | T19: 12 | U19: 7 | V19: 14 | W19: 0.818 | X19: 0.737 | Y19: 1.442 | Z19: 2.904 | AA19: 5.54 | AB19: 12.8
A20: 18832507 | B20: 900850 | C20: EVERYDAY CREME A CAFE (CUPS) 20 X 10 GR | E20: 5400141167900 | H20: DE04015011 | I20: 1 | J20: 5 | K20: 5 | L20: 1.145 | M20: 1.031 | N20: 0.746 | O20: 3.73 | P20: 0.58 | Q20: 2.9 | S20: BD62046290 | T20: 2 | U20: 3 | V20: 3 | W20: 1.74 | X20: 1.566 | Y20: 5.75 | Z20: 8.5 | AA20: 15.33 | AB20: 22.73
A21: 18832507 | B21: 900216 | C21: B/100 FEUILLES ETIQUET. PALETTE POUBELLE | H21: BE48219010 | I21: 1 | J21: 1 | K21: 1 | L21: 0.01 | M21: 0.009 | N21: 0.45 | O21: 0.45 | P21: 11.02 | Q21: 11.02 | S21: IN61152900 | T21: 2 | U21: 1 | V21: 2 | W21: 0.334 | X21: 0.301 | Y21: 1.386 | Z21: 2.772 | AA21: 2.58 | AB21: 5.16
A22: 18832507 | B22: 900774 | C22: CARTON AMERICAIN | H22: FR48191000 | I22: 10 | J22: 5 | K22: 50 | L22: 10 | M22: 9 | N22: 8.55 | O22: 427.5 | P22: 2.58 | Q22: 129 | S22: IN61142000 | T22: 2 | U22: 1 | V22: 2 | W22: 0.352 | X22: 0.317 | Y22: 1.176 | Z22: 2.352 | AA22: 2.55 | AB22: 5.1
A23: 18832507 | B23: 901050 | C23: BONI ASSORTIMENT MELANGE 500GR | H23: BE19053199 | I23: 1 | J23: 5 | K23: 5 | L23: 3.13 | M23: 2.817 | N23: 2.97 | O23: 14.85 | P23: 2.85 | Q23: 14.25 | S23: BD61109090 | T23: 56 | U23: 18 | V23: 60 | W23: 16.601 | X23: 14.941 | Y23: 41.609 | Z23: 160.584 | AA23: 69.61 | AB23: 306.57
A24: 18832507 | B24: 900781 | C24: MAXI SACS | H24: FR39232100 | I24: 25 | J24: 3 | K24: 75 | L24: 25.125 | M24: 22.613 | N24: 3 | O24: 225 | P24: 1.22 | Q24: 91.5 | S24: IN61091000 | T24: 52 | U24: 11 | V24: 58 | W24: 10.234 | X24: 9.21 | Y24: 15.041 | Z24: 98.02 | AA24: 31.95 | AB24: 207.82
A25: 18832517 | B25: 915273 | C25: EDP 50ML. ORIENTAL | E25: 8715658440048 | H25: CN33030010 | I25: 1 | J25: 2 | K25: 2 | L25: 2.424 | M25: 2.182 | N25: 4 | O25: 8 | P25: 1.83 | Q25: 3.66 | S25: PK61101990 | T25: 2 | U25: 1 | V25: 2 | W25: 0.86 | X25: 0.774 | Y25: 3.52 | Z25: 7.04 | AA25: 4.77 | AB25: 9.54
A26: 18832517 | B26: 283973 | C26: BYPHASSE DISSOLVANT 250ML ESSENTIALS | E26: 8436097092703 | F26: 8437005723306 | G26: 8436097093984 | H26: ES33043000 | I26: 1 | J26: 5 | K26: 5 | L26: 1.335 | M26: 1.202 | N26: 0.507 | O26: 2.535 | P26: 0.69 | Q26: 3.45 | S26: CN61103010 | T26: 13 | U26: 3 | V26: 13 | W26: 3.146 | X26: 2.831 | Y26: 8.442 | Z26: 34.152 | AA26: 17.42 | AB26: 76.52
A27: 18832651 | B27: 700322 | C27: PR JEANS REGULAR FIT DENIM NOIR | H27: BD62046390 | I27: 1 | J27: 1 | K27: 1 | L27: 0.471 | M27: 0.424 | N27: 2.533 | O27: 2.533 | P27: 7.47 | Q27: 7.47 | S27: HK61046900 | T27: 1 | U27: 2 | V27: 2 | W27: 0.592 | X27: 0.533 | Y27: 2.285 | Z27: 4.57 | AA27: 3.17 | AB27: 6.34
A28: 18832651 | B28: 991150 | C28: PR CEINT DGT NOIR Silver | H28: CN39262000 | I28: 2 | J28: 1 | K28: 2 | L28: 0.244 | M28: 0.22 | N28: 0.442 | O28: 0.884 | P28: 1.05 | Q28: 2.1 | S28: BD62034231 | T28: 4 | U28: 4 | V28: 4 | W28: 2.187 | X28: 1.969 | Y28: 9.445 | Z28: 9.445 | AA28: 27.83 | AB28: 27.83
A29: 18832651 | B29: 659963 | C29: PR PANT DROIT STRETCH GRIS | H29: BD62046290 | I29: 1 | J29: 1 | K29: 1 | L29: 0.497 | M29: 0.447 | N29: 3 | O29: 3 | P29: 7.93 | Q29: 7.93 | S29: IN61034900 | T29: 3 | U29: 3 | V29: 3 | W29: 0.816 | X29: 0.734 | Y29: 5.76 | Z29: 5.76 | AA29: 8.13 | AB29: 8.13
A30: 18832651 | B30: 635597 | C30: PR LEGGING LONG NOIR | H30: IN61152900 | I30: 2 | J30: 1 | K30: 2 | L30: 0.334 | M30: 0.301 | N30: 1.386 | O30: 2.772 | P30: 2.58 | Q30: 5.16 | S30: PK61101910 | T30: 26 | U30: 6 | V30: 26 | W30: 10.517 | X30: 9.465 | Y30: 14.809 | Z30: 48.539 | AA30: 36.25 | AB30: 158.05
A31: 18832651 | B31: 942303 | C31: HR LEGGING DARK GREY MEL | H31: IN61142000 | I31: 2 | J31: 1 | K31: 2 | L31: 0.352 | M31: 0.317 | N31: 1.176 | O31: 2.352 | P31: 2.55 | Q31: 5.1 | S31: CN61152900 | T31: 5 | U31: 12 | V31: 12 | W31: 0.764 | X31: 0.687 | Y31: 2.496 | Z31: 5.028 | AA31: 4.95 | AB31: 11.74
A32: 18832651 | B32: 700245 | C32: HR Cardigan Polar ftte turquoise | H32: BD61109090 | I32: 1 | J32: 1 | K32: 1 | L32: 0.136 | M32: 0.122 | N32: 1.8 | O32: 1.8 | P32: 2.86 | Q32: 2.86 | S32: CN61159500 | T32: 30 | U32: 5 | V32: 42 | W32: 5.232 | X32: 4.709 | Y32: 3.914 | Z32: 37.156 | AA32: 5.66 | AB32: 61.12
A33: 18832651 | B33: 700243 | C33: HR Cardigan Polar ftte bleu nuit | H33: BD61109090 | I33: 1 | J33: 1 | K33: 1 | L33: 0.204 | M33: 0.184 | N33: 2.4 | O33: 2.4 | P33: 2.93 | Q33: 2.93 | S33: PL61152100 | T33: 11 | U33: 3 | V33: 11 | W33: 0.709 | X33: 0.638 | Y33: 1.869 | Z33: 7.021 | AA33: 3.07 | AB33: 11.41
A34: 18832651 | B34: 700247 | C34: HR Cardigan Polar fille rose | H34: BD61109090 | I34: 1 | J34: 1 | K34: 1 | L34: 0.333 | M34: 0.3 | N34: 2.666 | O34: 2.666 | P34: 3.6 | Q34: 3.6 | S34: CN61082100 | T34: 18 | U34: 6 | V34: 20 | W34: 1.607 | X34: 1.447 | Y34: 2.848 | Z34: 12.637 | AA34: 6.71 | AB34: 33.75
A35: 18832651 | B35: 380893 | C35: PR tshirt fines brides cot-ea noir | H35: IN61091000 | I35: 2 | J35: 1 | K35: 2 | L35: 0.224 | M35: 0.202 | N35: 1.2 | O35: 2.4 | P35: 1.03 | Q35: 2.06 | S35: CN61089200 | T35: 6 | U35: 3 | V35: 6 | W35: 0.462 | X35: 0.416 | Y35: 1.797 | Z35: 3.594 | AA35: 4.31 | AB35: 8.62
A36: 18832651 | B36: 991151 | C36: PR CEINT DGT CAMEL Gold | H36: CN39262000 | I36: 2 | J36: 1 | K36: 2 | L36: 0.24 | M36: 0.216 | N36: 0.442 | O36: 0.884 | P36: 1.05 | Q36: 2.1 | S36: PL61152200 | T36: 4 | U36: 1 | V36: 4 | W36: 0.3 | X36: 0.27 | Y36: 0.541 | Z36: 2.164 | AA36: 1.22 | AB36: 4.88
A37: 18832651 | B37: 745081 | C37: PR CARDIGAN MOLLETON VIEUX ROSE | H37: PK61101990 | I37: 2 | J37: 1 | K37: 2 | L37: 0.86 | M37: 0.774 | N37: 3.52 | O37: 7.04 | P37: 4.77 | Q37: 9.54 | S37: CN61082200 | T37: 18 | U37: 6 | V37: 20 | W37: 1.705 | X37: 1.533 | Y37: 0.833 | Z37: 1.531 | AA37: 9.93 | AB37: 53.33
A38: 18832651 | B38: 380904 | C38: HR Polar cintré full zip NOIR | H38: CN61103010 | I38: 1 | J38: 1 | K38: 1 | L38: 0.35 | M38: 0.315 | N38: 3.3 | O38: 3.3 | P38: 5.6 | Q38: 5.6 | S38: CN61153090 | T38: 4 | U38: 1 | V38: 4 | W38: 0.248 | X38: 0.223 | Y38: 0.496 | Z38: 1.984 | AA38: 1.17 | AB38: 4.68
... A58: 18832651 | B58: 707862 | C58: HR Collant micro Fille LiLi Marine | H58: PL61152100 | I58: 3 | J58: 1 | K58: 3 | L58: 0.129 | M58: 0.116 | N58: 0.455 | O58: 1.365 | P58: 0.87 | Q58: 2.61 | S58: NL48030090 | T58: 1 | U58: 6 | V58: 6 | W58: 0.33 | X58: 0.297 | Y58: 0.545 | Z58: 3.27 | AA58: 0.59 | AB58: 3.54
A59: 18832651 | B59: 991176 | C59: PT lot 3 culottes Frozen | E59: 8720193921013 | H59: CN61082100 | I59: 12 | J59: 1 | K59: 12 | L59: 0.852 | M59: 0.767 | N59: 0.585 | O59: 7.02 | P59: 1.78 | Q59: 21.36 | S59: SY34011900 | T59: 1 | U59: 2 | V59: 2 | W59: 2.306 | X59: 2.075 | Y59: 4.333 | Z59: 8.666 | AA59: 10.02 | AB59: 20.04
A60: 18832651 | B60: 613275 | C60: PR V10 Brassière large bret noir | H60: CN61089200 | I60: 2 | J60: 1 | K60: 2 | L60: 0.172 | M60: 0.155 | N60: 0.771 | O60: 1.542 | P60: 1.4 | Q60: 2.8 | S60: IT70134999 | T60: 2 | U60: 10 | V60: 10 | W60: 8.015 | X60: 7.214 | Y60: 6.993 | Z60: 34.965 | AA60: 4.73 | AB60: 23.65
A61: 18832651 | B61: 613302 | C61: PR V10 Culotte dentelle ss cout noir | H61: CN61089200 | I61: 2 | J61: 1 | K61: 2 | L61: 0.144 | M61: 0.13 | N61: 0.472 | O61: 0.944 | P61: 1.37 | Q61: 2.74 | S61: NL70132890 | T61: 1 | U61: 1 | V61: 1 | W61: 0.39 | X61: 0.351 | Y61: 6.183 | Z61: 6.183 | AA61: 2.38 | AB61: 2.38
A62: 18832651 | B62: 664022 | C62: PR Collant microfibre 60D Noir | H62: PL61152200 | I62: 4 | J62: 1 | K62: 4 | L62: 0.3 | M62: 0.27 | N62: 0.541 | O62: 2.164 | P62: 1.22 | Q62: 4.88 | S62: IT70133799 | T62: 6 | U62: 2 | V62: 12 | W62: 3.996 | X62: 3.596 | Y62: 0.736 | Z62: 8.832 | AA62: 1.04 | AB62: 12.48
A63: 18832651 | B63: 913369 | C63: PR Collant massage mimat mo, NATURAL, XL | E63: 2090001191348 | H63: PL61152100 | I63: 4 | J63: 1 | K63: 4 | L63: 0.34 | M63: 0.306 | N63: 0.84 | O63: 3.36 | P63: 1.27 | Q63: 5.08 | S63: IT82100000 | T63: 1 | U63: 1 | V63: 1 | W63: 0.803 | X63: 0.723 | Y63: 10.5 | Z63: 10.5 | AA63: 11.16 | AB63: 11.16
A64: 18832651 | B64: 663985 | C64: PR Collant lycra satiné 20D Noir | H64: PL61152100 | I64: 4 | J64: 1 | K64: 4 | L64: 0.24 | M64: 0.216 | N64: 0.574 | O64: 2.296 | P64: 0.93 | Q64: 3.72 | S64: CN76151080 | T64: 9 | U64: 2 | V64: 9 | W64: 4.404 | X64: 3.963 | Y64: 8.561 | Z64: 33.306 | AA64: 7.03 | AB64: 25.92
A65: 18832651 | B65: 684517 | C65: PR String lazer cut chair PA/EA | H65: CN61082200 | I65: 1 | J65: 3 | K65: 3 | L65: 0.083 | M65: 0.074 | N65: 0.342 | O65: 1.026 | P65: 1.19 | Q65: 3.57 | S65: FR76151080 | T65: 1 | U65: 2 | V65: 2 | W65: 2.772 | X65: 2.495 | Y65: 9.25 | Z65: 18.5 | AA65: 21.47 | AB65: 42.94
A66: 18832651 | B66: 638821 | C66: PR Gaine dame ventre plat noir | H66: CN61082100 | I66: 1 | J66: 1 | K66: 1 | L66: 0.103 | M66: 0.093 | N66: 1.006 | O66: 1.006 | P66: 2.18 | Q66: 2.18 | S66: CN82152010 | T66: 10 | U66: 1 | V66: 10 | W66: 1.49 | X66: 1.341 | Y66: 0.184 | Z66: 1.84 | AA66: 1.3 | AB66: 13
A67: 18832651 | B67: 663875 | C67: PR Lot 5 mi-bas voile chif 20D Beige | E67: 2090000943962 | H67: CN61153090 | I67: 4 | J67: 1 | K67: 4 | L67: 0.248 | M67: 0.223 | N67: 0.496 | O67: 1.984 | P67: 1.17 | Q67: 4.68 | S67: CN96170000 | T67: 1 | U67: 3 | V67: 3 | W67: 1.749 | X67: 1.574 | Y67: 3.217 | Z67: 9.651 | AA67: 6.48 | AB67: 19.44
A68: 18832651 | B68: 664011 | C68: PR Collant Lycra mat antimaille fil Noir | H68: CN61152100 | I68: 4 | J68: 1 | K68: 4 | L68: 0.248 | M68: 0.223 | N68: 0.426 | O68: 1.704 | P68: 1.4 | Q68: 5.6 | S68: CN39233010 | T68: 1 | U68: 3 | V68: 3 | W68: 0.225 | X68: 0.203 | Y68: 1.127 | Z68: 3.381 | AA68: 1.03 | AB68: 3.09
A69: 18832651 | B69: 380510 | C69: PT Lot 2 culottes D noirs DISCRET | H69: CN61082100 | I69: 4 | J69: 1 | K69: 4 | L69: 0.484 | M69: 0.436 | N69: 0.84 | O69: 3.36 | P69: 1.96 | Q69: 7.84 | S69: CN69120023 | T69: 9 | U69: 15 | V69: 20 | W69: 14.58 | X69: 13.122 | Y69: 10.64 | Z69: 53.984 | AA69: 18.85 | AB69: 96.72
A70: 18832651 | B70: 361405 | C70: PT lot 2 slips noir | H70: CN61082100 | I70: 1 | J70: 3 | K70: 3 | L70: 0.168 | M70: 0.151 | N70: 0.417 | O70: 1.251 | P70: 0.79 | Q70: 2.37 | S70: CN85167970 | T70: 4 | U70: 5 | V70: 5 | W70: 7.453 | X70: 6.708 | Y70: 42.578 | Z70: 59.543 | AA70: 35.46 | AB70: 50.36
A71: 18832651 | B71: 987061 | C71: PR Brassière large bretelle PRUNE MALAGA | H71: CN62121010 | I71: 2 | J71: 1 | K71: 2 | L71: 0.174 | M71: 0.157 | N71: 0.588 | O71: 1.176 | P71: 1.74 | Q71: 3.48 | S71: ES39269097 | T71: 12 | U71: 1 | V71: 12 | W71: 0.9 | X71: 0.81 | Y71: 0.5 | Z71: 6 | AA71: 0.54 | AB71: 6.48
A72: 18832651 | B72: 603405 | C72: PR Lot 2 SG white / Black micro + dent | H72: CN62121090 | I72: 1 | J72: 1 | K72: 1 | L72: 0.295 | M72: 0.266 | N72: 2.97 | O72: 2.97 | P72: 5.8 | Q72: 5.8 | S72: PL39249000 | T72: 1 | U72: 3 | V72: 3 | W72: 0.759 | X72: 0.683 | Y72: 3.523 | Z72: 10.569 | AA72: 1.79 | AB72: 5.37
A73: 18832651 | B73: 986959 | C73: HR 70564 SG A/A ARUM VERT OMBRE | H73: CN62121090 | I73: 1 | J73: 1 | K73: 1 | L73: 0.103 | M73: 0.093 | N73: 1.533 | O73: 1.533 | P73: 11.76 | Q73: 11.76 | S73: CN70109010 | T73: 1 | U73: 4 | V73: 4 | W73: 3.612 | X73: 3.251 | Y73: 4.94 | Z73: 19.76 | AA73: 2.12 | AB73: 8.48
A74: 18832651 | B74: 755783 | C74: PR Brassière large bret gris chiné | H74: CN61089200 | I74: 2 | J74: 1 | K74: 2 | L74: 0.146 | M74: 0.131 | N74: 0.554 | O74: 1.108 | P74: 1.54 | Q74: 3.08 | S74: TR70133799 | T74: 1 | U74: 2 | V74: 2 | W74: 1.416 | X74: 1.274 | Y74: 6.856 | Z74: 13.712 | AA74: 3.34 | AB74: 6.68
A75: 18832651 | B75: 707645 | C75: PT lot 3 tennis terry Fila blanc | H75: PT61159500 | I75: 4 | J75: 1 | K75: 4 | L75: 0.868 | M75: 0.781 | N75: 1.84 | O75: 7.36 | P75: 2.4 | Q75: 9.6 | S75: FR48236910 | T75: 1 | U75: 5 | V75: 5 | W75: 4.9 | X75: 4.41 | Y75: 3.571 | Z75: 17.855 | AA75: 2.02 | AB75: 10.1
A76: 18832651 | B76: 725821 | C76: PR PYJASHORT JERSEY NAVY | H76: BD61031090 | I76: 1 | J76: 1 | K76: 1 | L76: 0.358 | M76: 0.322 | N76: 1.642 | O76: 1.642 | P76: 4.26 | Q76: 4.26 | S76: CN70133799 | T76: 1 | U76: 6 | V76: 6 | W76: 1.89 | X76: 1.702 | Y76: 1.75 | Z76: 10.5 | AA76: 3.81 | AB76: 22.86
A77: 18832651 | B77: 750120 | C77: PR SC ceinture PU brun 3cm | E77: 2090001128054 | H77: CN61091000 | I77: 5 | J77: 1 | K77: 5 | L77: 0.635 | M77: 0.572 | N77: 0.5 | O77: 2.5 | P77: 1.1 | Q77: 5.5 | S77: TR69111000 | T77: 6 | U77: 1 | V77: 6 | W77: 4.146 | X77: 3.731 | Y77: 1.5 | Z77: 9 | AA77: 1.28 | AB77: 7.68
A78: 18832651 | B78: 659967 | C78: PR PANT DROIT STRETCH NOIR | H78: BD62046290 | I78: 1 | J78: 2 | K78: 2 | L78: 1.243 | M78: 1.119 | N78: 2.75 | O78: 5.5 | P78: 7.4 | Q78: 14.8 | S78: CN68030090 | T78: 112 | U78: 18 | V78: 128 | W78: 118.68 | X78: 106.812 | Y78: 1.457 | Z78: 86.956 | AA78: 1.61 | AB78: 105.64
A79: 18832651 | B79: 655050 | C79: HR POLAR FULL ZIP MAUVE | H79: BD61109090 | I79: 2 | J79: 2 | K79: 4 | L79: 1.91 | M79: 1.719 | N79: 5.166 | O79: 20.664 | P79: 5.46 | Q79: 21.84 | S79: FR33021010 | T79: 2 | U79: 7 | V79: 7 | W79: 0.113 | X79: 0.102 | Y79: 0.14 | Z79: 0.485 | AA79: 4.93 | AB79: 17.24
A80: 18832651 | B80: 727156 | C80: PT Lot 5 cho7 PB | H80: CN61159500 | I80: 4 | J80: 1 | K80: 4 | L80: 0.7 | M80: 0.63 | N80: 0.772 | O80: 3.088 | P80: 1.26 | Q80: 5.04 | S80: CN85434000 | T80: 8 | U80: 24 | V80: 24 | W80: 0.883 | X80: 0.796 | Y80: 0.749 | Z80: 2.225 | AA80: 23.67 | AB80: 70.98
A81: 18832651 | B81: 743935 | C81: HT collant BB écru | H81: CN61152900 | I81: 1 | J81: 2 | K81: 2 | L81: 0.108 | M81: 0.097 | N81: 0.304 | O81: 0.608 | P81: 0.96 | Q81: 1.92 | S81: DE56012290 | T81: 21 | U81: 1 | V81: 21 | W81: 0.924 | X81: 0.832 | Y81: 0.843 | Z81: 17.703 | AA81: 0.39 | AB81: 8.19
A82: 18832651 | B82: 606328 | C82: PR Lot 2 boxers désaiguillés N+B PA/EA | H82: CN61082200 | I82: 1 | J82: 1 | K82: 1 | L82: 0.086 | M82: 0.077 | N82: 0.489 | O82: 0.489 | P82: 2.88 | Q82: 2.88 | S82: DE38249996 | T82: 1 | U82: 8 | V82: 8 | W82: 35.2 | X82: 31.68 | Y82: 12 | Z82: 96 | AA82: 3.35 | AB82: 26.8
A83: 18832651 | B83: 692488 | C83: PR Collant lycra semi-glossy 15 NOIR XXL | E83: 2090001004433 | H83: BE61152100 | I83: 4 | J83: 1 | K83: 4 | L83: 0.252 | M83: 0.227 | N83: 0.638 | O83: 2.552 | P83: 0.82 | Q83: 3.28 | S83: HU23099096 | T83: 11 | U83: 5 | V83: 14 | W83: 7.58 | X83: 6.822 | Y83: 5.978 | Z83: 26.18 | AA83: 3.43 | AB83: 18.16
A84: 18832651 | B84: 725798 | C84: PR PYJASHORT JERSEY BORDEAUX | H84: BD61031090 | I84: 1 | J84: 1 | K84: 1 | L84: 0.316 | M84: 0.284 | N84: 1.642 | O84: 1.642 | P84: 4.21 | Q84: 4.21 | S84: BE23099096 | T84: 2 | U84: 5 | V84: 9 | W84: 23.724 | X84: 21.351 | Y84: 7.84 | Z84: 43.68 | AA84: 4.24 | AB84: 20.78
A85: 18832651 | B85: 600227 | C85: PT lot 3 tennis Puma homme | H85: NL61159500 | I85: 1 | J85: 3 | K85: 3 | L85: 0.692 | M85: 0.623 | N85: 1.533 | O85: 4.6 | P85: 3.5 | Q85: 10.5 | S85: CN63079010 | T85: 1 | U85: 1 | V85: 1 | W85: 0.837 | X85: 0.753 | Y85: 12.09 | Z85: 12.09 | AA85: 7.57 | AB85: 7.57
A86: 18832651 | B86: 752671 | C86: HT lot 2 heat socks viscose | E86: 2090001134116 | H86: CN61152100 | I86: 5 | J86: 1 | K86: 5 | L86: 1.325 | M86: 1.193 | N86: 2.136 | O86: 10.68 | P86: 2.13 | Q86: 10.65 | S86: CN42010000 | T86: 1 | U86: 2 | V86: 2 | W86: 0.276 | X86: 0.248 | Y86: 0.83 | Z86: 1.66 | AA86: 1.87 | AB86: 3.74
A87: 18832651 | B87: 683902 | C87: PT Lot 2 slips gris chiné CO | H87: CN61071100 | I87: 1 | J87: 3 | K87: 3 | L87: 0.552 | M87: 0.497 | N87: 1.344 | O87: 4.032 | P87: 1.88 | Q87: 5.64 | S87: FR23091090 | T87: 1 | U87: 5 | V87: 5 | W87: 0.58 | X87: 0.522 | Y87: 0.756 | Z87: 3.78 | AA87: 1.69 | AB87: 8.45
A88: 18832651 | B88: 663873 | C88: PR Lot 2 mibas mous+bord confor 20D Auba | E88: 2090000943955 | H88: PL61153011 | I88: 4 | J88: 1 | K88: 4 | L88: 0.132 | M88: 0.119 | N88: 0.276 | O88: 1.104 | P88: 0.64 | Q88: 2.56 | S88: FR33079000 | T88: 2 | U88: 6 | V88: 6 | W88: 1.46 | X88: 1.314 | Y88: 0.876 | Z88: 2.674 | AA88: 6.91 | AB88: 23.08
A89: 18832651 | B89: 663864 | C89: PR Lot 2 socq voile repass 20D Noir | E89: 2090000943863 | H89: PL61153019 | I89: 4 | J89: 1 | K89: 4 | L89: 0.108 | M89: 0.097 | N89: 0.345 | O89: 1.38 | P89: 0.81 | Q89: 3.24 | S89: CN85094000 | T89: 2 | U89: 2 | V89: 2 | W89: 3.852 | X89: 3.466 | Y89: 21.234 | Z89: 21.234 | AA89: 24.3 | AB89: 24.3
A90: 18832651 | B90: 659181 | C90: HR lot 2 cho7 Slazenger High Performance | E90: 2090000925111 | H90: CN61159500 | I90: 10 | J90: 1 | K90: 10 | L90: 1.52 | M90: 1.368 | N90: 1.5 | O90: 15 | P90: 1.88 | Q90: 18.8 | S90: CN85166070 | T90: 2 | U90: 2 | V90: 2 | W90: 9.23 | X90: 8.307 | Y90: 72.188 | Z90: 72.188 | AA90: 133.21 | AB90: 133.21
A91: 18832651 | B91: 725822 | C91: PR PYJASHORT WOVEN GRIS | H91: PK61032200 | I91: 1 | J91: 2 | K91: 2 | L91: 0.72 | M91: 0.648 | N91: 3.2 | O91: 6.4 | P91: 4.21 | Q91: 8.42 | S91: CN48171000 | T91: 10 | U91: 1 | V91: 10 | W91: 2.08 | X91: 1.872 | Y91: 0.637 | Z91: 6.37 | AA91: 0.9 | AB91: 9
A92: 18832916 | B92: 1020700 | C92: BOITE PAIN PS+BAM FRESHEAT | E92: 3560237583907 | H92: CN44191900 | I92: 1 | J92: 1 | K92: 1 | L92: 0.865 | M92: 0.779 | N92: 11.22 | O92: 11.22 | P92: 5.08 | Q92: 5.08 | S92: CN39269097 | T92: 2 | U92: 4 | V92: 4 | W92: 1.006 | X92: 0.905 | Y92: 8.075 | Z92: 16.15 | AA92: 6.07 | AB92: 12.14
A93: 18832916 | B93: 682224 | C93: BOITE A CLIPS RECT. 1,6L | E93: 2090000979121 | H93: CN39241000 | I93: 1 | J93: 2 | K93: 2 | L93: 0.54 | M93: 0.486 | N93: 3.263 | O93: 6.526 | P93: 2.11 | Q93: 4.22 | S93: CN85444290 | T93: 1 | U93: 3 | V93: 3 | W93: 0.198 | X93: 0.178 | Y93: 0.44 | Z93: 1.32 | AA93: 1.3 | AB93: 3.9
A94: 18832916 | B94: 949306 | C94: LUNCHBOX 3EN1 Rose | E94: 5410801113000 | H94: BE39241000 | I94: 1 | J94: 3 | K94: 3 | L94: 0.84 | M94: 0.756 | N94: 3.645 | O94: 10.935 | P94: 3.7 | Q94: 11.1 | S94: CN85182100 | T94: 1 | U94: 1 | V94: 1 | W94: 0.6 | X94: 0.54 | Y94: 5.316 | Z94: 5.316 | AA94: 5.9 | AB94: 5.9
A95: 18832916 | B95: 1001570 | C95: SUPPORT ESS-TOUT FIL H30CM | E95: 3664944388197 | H95: CN73239900 | I95: 1 | J95: 2 | K95: 2 | L95: 0.504 | M95: 0.454 | N95: 1.249 | O95: 2.498 | P95: 1.37 | Q95: 2.74 | S95: CN95044000 | T95: 1 | U95: 1 | V95: 1 | W95: 0.458 | X95: 0.412 | Y95: 3.375 | Z95: 3.375 | AA95: 1.3 | AB95: 1.3
A96: 18832916 | B96: 708113 | C96: BICARBONATE DE SOUDE 1 KG FOREVER | E96: 5400191808723 | H96: BE28363000 | I96: 1 | J96: 3 | K96: 3 | L96: 3.318 | M96: 2.986 | N96: 2.057 | O96: 6.171 | P96: 3.35 | Q96: 10.05 | S96: CZ95030095 | T96: 1 | U96: 2 | V96: 2 | W96: 0.632 | X96: 0.568 | Y96: 4.84 | Z96: 9.68 | AA96: 3.8 | AB96: 7.6
A97: 18832916 | B97: 986642 | C97: EPONGE VEG GRAT TOU SURF X3 | E97: 5410721515168 | H97: FR68053000 | I97: 16 | J97: 1 | K97: 16 | L97: 1.12 | M97: 1.008 | N97: 0.587 | O97: 9.392 | P97: 0.63 | Q97: 10.08 | S97: TH95030070 | T97: 1 | U97: 1 | V97: 1 | W97: 0.175 | X97: 0.158 | Y97: 0.862 | Z97: 0.862 | AA97: 10.51 | AB97: 10.51
A98: 18832916 | B98: 746305 | C98: LAVETTE MF COLORS X 8 | E98: 4023103185975 | H98: CN63071010 | I98: 1 | J98: 3 | K98: 3 | L98: 0.732 | M98: 0.659 | N98: 2.016 | O98: 6.048 | P98: 4.65 | Q98: 13.95 | S98: CN95030055 | T98: 9 | U98: 19 | V98: 19 | W98: 13.584 | X98: 12.226 | Y98: 74.037 | Z98: 155.501 | AA98: 61.31 | AB98: 123.11
A99: 18832916 | B99: 772930 | C99: GEL WC DETARTRANT ECOLOGIQUE | E99: 3563210022288 | H99: FR34025090 | I99: 1 | J99: 2 | K99: 2 | L99: 1.74 | M99: 1.566 | N99: 1.666 | O99: 3.332 | P99: 2.54 | Q99: 5.08 | S99: CN95030070 | T99: 94 | U99: 84 | V99: 150 | W99: 128.699 | X99: 115.825 | Y99: 459.101 | Z99: 1634.581 | AA99: 305.96 | AB99: 1197.76
A100: 18832916 | B100: 302565 | C100: 2 EPONGES A RECURER VEGETALES BLEU | E100: 8710648172022 | H100: NL48030090 | I100: 1 | J100: 6 | K100: 6 | L100: 0.33 | M100: 0.297 | N100: 0.545 | O100: 3.27 | P100: 0.59 | Q100: 3.54 | S100: CZ95030035 | T100: 5 | U100: 6 | V100: 6 | W100: 1.645 | X100: 1.481 | Y100: 12.564 | Z100: 14.004 | AA100: 46.26 | AB100: 51.8
A101: 18832916 | B101: 624895 | C101: Savon d'Alep vrac 1kg | E101: 3593290025718 | H101: SY34011900 | I101: 1 | J101: 2 | K101: 2 | L101: 2.306 | M101: 2.075 | N101: 4.333 | O101: 8.666 | P101: 10.02 | Q101: 20.04 | S101: DE95030070 | T101: 1 | U101: 2 | V101: 2 | W101: 0.6 | X101: 0.54 | Y101: 3.952 | Z101: 7.904 | AA101: 13.27 | AB101: 26.54
A102: 18832916 | B102: 342217 | C102: BICARBONATE DE SOUDE 500G | E102: 5400191806583 | H102: BE28363000 | I102: 6 | J102: 1 | K102: 6 | L102: 3.438 | M102: 3.094 | N102: 0.891 | O102: 5.346 | P102: 1.87 | Q102: 11.22 | S102: VN95030021 | T102: 1 | U102: 1 | V102: 1 | W102: 0.205 | X102: 0.185 | Y102: 2.64 | Z102: 2.64 | AA102: 9.42 | AB102: 9.42
A103: 18832916 | B103: 944588 | C103: CARAFE 1L MISURA VER | E103: 11381000626 | F103: 8001133841708 | H103: IT70134999 | I103: 1 | J103: 5 | K103: 5 | L103: 4.25 | M103: 3.825 | N103: 4.375 | O103: 21.875 | P103: 1.99 | Q103: 9.95 | S103: BE17049071 | T103: 6 | U103: 1 | V103: 6 | W103: 1.476 | X103: 1.328 | Y103: 0.884 | Z103: 5.304 | AA103: 1.34 | AB103: 8.04
A104: 18832916 | B104: 943166 | C104: 2 VERRES A MARTINI 26CL | E104: 3491955565008 | H104: NL70132890 | I104: 1 | J104: 1 | K104: 1 | L104: 0.39 | M104: 0.351 | N104: 6.183 | O104: 6.183 | P104: 2.38 | Q104: 2.38 | S104: BE19053119 | T104: 20 | U104: 1 | V104: 20 | W104: 1.34 | X104: 1.206 | Y104: 0.228 | Z104: 4.56 | AA104: 0.44 | AB104: 8.8
A105: 18832916 | B105: 955600 | C105: DIAMOND GOBELET 30CL OCEAN BLUE | E105: 8004360065022 | H105: IT70133799 | I105: 6 | J105: 2 | K105: 12 | L105: 3.996 | M105: 3.596 | N105: 0.736 | O105: 8.832 | P105: 1.04 | Q105: 12.48 | S105: BE17049065 | T105: 115 | U105: 14 | V105: 227 | W105: 30.596 | X105: 27.536 | Y105: 4.305 | Z105: 149.463 | AA105: 4.59 | AB105: 153.84
A106: 18832916 | B106: 919303 | C106: PASSE LEGUMES EN INOX DIA.24CM | E106: 8032797730299 | H106: IT82100000 | I106: 1 | J106: 1 | K106: 1 | L106: 0.803 | M106: 0.723 | N106: 10.5 | O106: 10.5 | P106: 11.16 | Q106: 11.16 | S106: IE17049061 | T106: 16 | U106: 1 | V106: 16 | W106: 1.04 | X106: 0.936 | Y106: 0.111 | Z106: 1.776 | AA106: 1.21 | AB106: 19.36
A107: 18832916 | B107: 743974 | C107: PRESSE PUREE PLIANT 29 CM INOX/PP | E107: 3560238519424 | H107: CN39241000 | I107: 1 | J107: 6 | K107: 6 | L107: 1.278 | M107: 1.15 | N107: 1.529 | O107: 9.174 | P107: 2.03 | Q107: 12.18 | S107: FR96081099 | T107: 1 | U107: 10 | V107: 10 | W107: 0.33 | X107: 0.297 | Y107: 0.168 | Z107: 1.68 | AA107: 1.4 | AB107: 14
A108: 18832916 | B108: 915281 | C108: TIRE BOUCHON ALPINA PP/CHROME | E108: 8711252170251 | H108: CN39241000 | I108: 1 | J108: 9 | K108: 9 | L108: 0.882 | M108: 0.794 | N108: 0.532 | O108: 4.788 | P108: 1.17 | Q108: 10.53 | S108: IT39261000 | T108: 1 | U108: 3 | V108: 3 | W108: 0.273 | X108: 0.246 | Y108: 1 | Z108: 3 | AA108: 0.89 | AB108: 2.67
A109: 18832916 | B109: 383537 | C109: POELE CERAM 24C TOUS FEUX+INDUCTION | E109: 2090000694062 | H109: CN76151080 | I109: 3 | J109: 1 | K109: 3 | L109: 2.538 | M109: 2.284 | N109: 6.02 | O109: 18.06 | P109: 5.42 | Q109: 16.26 | S109: FR33030090 | T109: 6 | U109: 1 | V109: 6 | W109: 1.278 | X109: 1.15 | Y109: 0.504 | Z109: 3.024 | AA109: 2.96 | AB109: 17.76
A110: 18832916 | B110: 1021417 | C110: Tough poêle 28 cm TEFAL | E110: 3168430344037 | H110: FR76151080 | I110: 1 | J110: 2 | K110: 2 | L110: 2.772 | M110: 2.495 | N110: 9.25 | O110: 18.5 | P110: 21.47 | Q110: 42.94 | S110: ES48131000 | T110: 1 | U110: 8 | V110: 8 | W110: 0.496 | X110: 0.446 | Y110: 0.362 | Z110: 2.896 | AA110: 0.7 | AB110: 5.6
A111: 18832916 | B111: 609054 | C111: MOULE DEMONTABLE ROND 26CM | E111: 3560239397731 | H111: CN73239900 | I111: 1 | J111: 3 | K111: 3 | L111: 1.608 | M111: 1.447 | N111: 7.02 | O111: 21.06 | P111: 2.65 | Q111: 7.95 | S111: BE48201030 | T111: 10 | U111: 1 | V111: 10 | W111: 4.2 | X111: 3.78 | Y111: 0.66 | Z111: 6.6 | AA111: 0.77 | AB111: 7.7
A112: 18832916 | B112: 372328 | C112: S6 CUILLERES CAFE ANDREA INOX MAESTRO | E112: 2090000642827 | H112: CN82152010 | I112: 10 | J112: 1 | K112: 10 | L112: 1.49 | M112: 1.341 | N112: 0.184 | O112: 1.84 | P112: 1.3 | Q112: 13 | S112: CN56075011 | T112: 1 | U112: 3 | V112: 3 | W112: 0.51 | X112: 0.459 | Y112: 1.127 | Z112: 3.381 | AA112: 1.47 | AB112: 4.41
A113: 18832916 | B113: 716998 | C113: SET DE TABLE WOVEN GRIS | E113: 3491955115005 | H113: CN39241000 | I113: 12 | J113: 1 | K113: 12 | L113: 0.936 | M113: 0.842 | N113: 0.156 | O113: 1.872 | P113: 0.53 | Q113: 6.36 | S113: BE34060000 | T113: 13 | U113: 11 | V113: 20 | W113: 18.06 | X113: 16.255 | Y113: 7.949 | Z113: 49.434 | AA113: 8.9 | AB113: 52.78
A114: 18832916 | B114: 969231 | C114: Bouteille isolante 1L avec silicone- 3 a | E114: 5400370127379 | H114: CN96170000 | I114: 1 | J114: 3 | K114: 3 | L114: 1.749 | M114: 1.574 | N114: 3.217 | O114: 9.651 | P114: 6.48 | Q114: 19.44 | S114: CN33074900 | T114: 2 | U114: 5 | V114: 5 | W114: 1.24 | X114: 1.116 | Y114: 4.977 | Z114: 7.812 | AA114: 5.07 | AB114: 9.63
A115: 18832916 | B115: 905014 | C115: GOURDE PLASTIQUE LOL 400ML | E115: 8412497168323 | H115: CN39233010 | I115: 1 | J115: 3 | K115: 3 | L115: 0.225 | M115: 0.203 | N115: 1.127 | O115: 3.381 | P115: 1.03 | Q115: 3.09 | S115: IN34060000 | T115: 2 | U115: 3 | V115: 6 | W115: 6.423 | X115: 5.781 | Y115: 4.732 | Z115: 14.196 | AA115: 10.05 | AB115: 30.25
... A126: 18832916 | B126: 943007 | C126: PICHET AVEC ANSE 1.1L | E126: 8001691575008 | H126: IT70134999 | I126: 1 | J126: 5 | K126: 5 | L126: 3.765 | M126: 3.389 | N126: 2.618 | O126: 13.09 | P126: 2.74 | Q126: 13.7 | S126: IT64019290 | T126: 3 | U126: 3 | V126: 4 | W126: 4.943 | X126: 4.449 | Y126: 15.219 | Z126: 30.438 | AA126: 9.41 | AB126: 18.82
A127: 18832916 | B127: 791844 | C127: 100 Assiet.carton 23cm Blanc | E127: 3353890795066 | F127: 3491953961666 | H127: FR48236910 | I127: 1 | J127: 5 | K127: 5 | L127: 4.9 | M127: 4.41 | N127: 3.571 | O127: 17.855 | P127: 2.02 | Q127: 10.1 | S127: CN64041910 | T127: 4 | U127: 2 | V127: 4 | W127: 1.058 | X127: 0.952 | Y127: 5.866 | Z127: 11.732 | AA127: 4.99 | AB127: 9.98
A128: 18832916 | B128: 949963 | C128: MUG MICRO-ONDES PAW PATROL | E128: 8412497189045 | H128: CN39241000 | I128: 1 | J128: 2 | K128: 2 | L128: 0.15 | M128: 0.135 | N128: 0.855 | O128: 1.71 | P128: 1.22 | Q128: 2.44 | S128: TR64029931 | T128: 1 | U128: 1 | V128: 1 | W128: 0.347 | X128: 0.312 | Y128: 4.263 | Z128: 4.263 | AA128: 2.61 | AB128: 2.61
A129: 18832916 | B129: 983320 | C129: POKEMON LUNCHBOX | E129: 8412497080748 | H129: CN39241000 | I129: 1 | J129: 2 | K129: 2 | L129: 0.226 | M129: 0.203 | N129: 1.805 | O129: 3.61 | P129: 1.28 | Q129: 2.56 | S129: CN73239300 | T129: 1 | U129: 2 | V129: 2 | W129: 1.142 | X129: 1.028 | Y129: 7.328 | Z129: 14.656 | AA129: 5.97 | AB129: 11.94
...

Sheet Séparer
H1: Code | I1: Origine | J1: Colisage | K1: #Colis | L1: #Pces | M1: Valeur Addition | N1: Poids Brut | O1: Poids Net | P1: Vol. Pce | Q1: Vol.Total | R1: PA Global
H2: 04015011 | I2: DE | J2: 1 | K2: 5 | L2: 5 | M2: =LOOKUP(H2,$W$4:$W$192,Séparer!$X$4:$X$192) -> 0 | N2: 1.145 | O2: 1.031 | P2: 0.746 | Q2: 3.73 | R2: 2.9
H3: 17049061 | I3: IE | J3: 16 | K3: 1 | L3: 16 | M3: =LOOKUP(H3,$W$4:$W$192,Séparer!$X$4:$X$192) -> 0 | N3: 1.04 | O3: 0.936 | P3: 0.111 | Q3: 1.776 | R3: 19.36
H4: 17049065 | I4: BE | J4: 115 | K4: 14 | L4: 227 | M4: =LOOKUP(H4,$W$4:$W$192,Séparer!$X$4:$X$192) -> 0 | N4: 30.596 | O4: 27.536 | P4: 4.305 | Q4: 149.463 | R4: 153.84 | W4: 04015011
H5: 17049065 | I5: ES | J5: 33 | K5: 4 | L5: 44 | M5: =LOOKUP(H5,$W$4:$W$192,Séparer!$X$4:$X$192) -> 0 | N5: 4.631 | O5: 4.168 | P5: 1.512 | Q5: 22.044 | R5: 31.68 | W5: 17049061
H6: 17049065 | I6: CN | J6: 24 | K6: 2 | L6: 24 | M6: =LOOKUP(H6,$W$4:$W$192,Séparer!$X$4:$X$192) -> 0 | N6: 6.6 | O6: 5.94 | P6: 5.4 | Q6: 64.8 | R6: 61.2 | W6: 17049065 | X6: 0
H7: 17049071 | I7: BE | J7: 6 | K7: 1 | L7: 6 | M7: =LOOKUP(H7,$W$4:$W$192,Séparer!$X$4:$X$192) -> 0 | N7: 1.476 | O7: 1.328 | P7: 0.884 | Q7: 5.304 | R7: 8.04 | W7: 17049071 | X7: 0
H8: 17049071 | I8: CN | J8: 2 | K8: 28 | L8: 28 | M8: =LOOKUP(H8,$W$4:$W$192,Séparer!$X$4:$X$192) -> 0 | N8: 56 | O8: 50.4 | P8: 20.202 | Q8: 282.828 | R8: 19.88 | W8: 18063100 | X8: 0
H9: 18063100 | I9: DE | J9: 6 | K9: 6 | L9: 104 | M9: =LOOKUP(H9,$W$4:$W$192,Séparer!$X$4:$X$192) -> 0 | N9: 46.384 | O9: 41.746 | P9: 14.744 | Q9: 247.392 | R9: 463.04 | W9: 18069019 | X9: 0
H10: 18069019 | I10: DE | J10: 2 | K10: 2 | L10: 54 | M10: =LOOKUP(H10,$W$4:$W$192,Séparer!$X$4:$X$192) -> 0 | N10: 12.042 | O10: 10.838 | P10: 2.666 | Q10: 71.982 | R10: 135.54 | W10: 18069031 | X10: 0
H11: 18069019 | I11: IT | J11: 2 | K11: 2 | L11: 60 | M11: =LOOKUP(H11,$W$4:$W$192,Séparer!$X$4:$X$192) -> 0 | N11: 3.6 | O11: 3.24 | P11: 0.198 | Q11: 5.94 | R11: 27 | W11: 18069039 | X11: 0
H12: 18069019 | I12: BE | J12: 4 | K12: 4 | L12: 176 | M12: =LOOKUP(H12,$W$4:$W$192,Séparer!$X$4:$X$192) -> 0 | N12: 15.952 | O12: 14.356 | P12: 1.514 | Q12: 72.176 | R12: 334.72 | W12: 18069060 | X12: 0
H13: 18069019 | I13: CH | J13: 28 | K13: 2 | L13: 28 | M13: =LOOKUP(H13,$W$4:$W$192,Séparer!$X$4:$X$192) -> 0 | N13: 5.376 | O13: 4.838 | P13: 3.7 | Q13: 51.8 | R13: 58.8 | W13: 19053119 | X13: 0
H14: 18069031 | I14: BE | J14: 10 | K14: 10 | L14: 208 | M14: =LOOKUP(H14,$W$4:$W$192,Séparer!$X$4:$X$192) -> 0 | N14: 38.076 | O14: 34.268 | P14: 14.212 | Q14: 314.768 | R14: 804.56 | W14: 19053199 | X14: 0
H15: 18069031 | I15: PL | J15: 4 | K15: 4 | L15: 176 | M15: =LOOKUP(H15,$W$4:$W$192,Séparer!$X$4:$X$192) -> 0 | N15: 7.656 | O15: 6.89 | P15: 1.606 | Q15: 73.112 | R15: 201.28 | W15: 20052020 | X15: 0
H16: 18069039 | I16: DE | J16: 64 | K16: 2 | L16: 64 | M16: =LOOKUP(H16,$W$4:$W$192,Séparer!$X$4:$X$192) -> 0 | N16: 9.984 | O16: 8.986 | P16: 1.874 | Q16: 59.968 | R16: 46.08 | W16: 21069051 | X16: 0
H17: 18069060 | I17: IT | J17: 128 | K17: 2 | L17: 128 | M17: =LOOKUP(H17,$W$4:$W$192,Séparer!$X$4:$X$192) -> 0 | N17: 9.088 | O17: 8.18 | P17: 0.25 | Q17: 16 | R17: 69.12 | W17: 21069059 | X17: 0
H18: 19053119 | I18: BE | J18: 20 | K18: 1 | L18: 20 | M18: =LOOKUP(H18,$W$4:$W$192,Séparer!$X$4:$X$192) -> 0 | N18: 1.34 | O18: 1.206 | P18: 0.228 | Q18: 4.56 | R18: 8.8 | W18: 22011090 | X18: LTR
H19: 19053199 | I19: BE | J19: 1 | K19: 5 | L19: 5 | M19: =LOOKUP(H19,$W$4:$W$192,Séparer!$X$4:$X$192) -> 0 | N19: 3.13 | O19: 2.817 | P19: 2.97 | Q19: 14.85 | R19: 14.25 | W19: 22021000 | X19: LTR
H20: 20052020 | I20: FR | J20: 20 | K20: 2 | L20: 20 | M20: =LOOKUP(H20,$W$4:$W$192,Séparer!$X$4:$X$192) -> 0 | N20: 3.1 | O20: 2.79 | P20: 5.64 | Q20: 56.4 | R20: 25.9 | W20: 23091090 | X20: 0
H21: 21069051 | I21: CH | J21: 1 | K21: 2 | L21: 2 | M21: =LOOKUP(H21,$W$4:$W$192,Séparer!$X$4:$X$192) -> 0 | N21: 0.08 | O21: 0.072 | P21: 0.239 | Q21: 0.478 | R21: 2.8 | W21: 23099096 | X21: 0
H22: 21069059 | I22: CN | J22: 48 | K22: 2 | L22: 48 | M22: =LOOKUP(H22,$W$4:$W$192,Séparer!$X$4:$X$192) -> 0 | N22: 6.168 | O22: 5.551 | P22: 0.765 | Q22: 18.36 | R22: 77.76 | W22: 28363000 | X22: 0
H23: 22011090 | I23: BE | J23: 6 | K23: 2 | L23: 12 | M23: =LOOKUP(H23,$W$4:$W$192,Séparer!$X$4:$X$192) -> LTR | N23: 6.3 | O23: 5.67 | P23: 0.937 | Q23: 11.244 | R23: 4.68 | W23: 30051000 | X23: 0
H24: 22021000 | I24: NL | J24: 12 | K24: 1 | L24: 12 | M24: =LOOKUP(H24,$W$4:$W$192,Séparer!$X$4:$X$192) -> LTR | N24: 4.74 | O24: 4.266 | P24: 0.52 | Q24: 6.24 | R24: 9.84 | W24: 33012949 | X24: 0
H25: 22021000 | I25: GB | J25: 24 | K25: 1 | L25: 24 | M25: =LOOKUP(H25,$W$4:$W$192,Séparer!$X$4:$X$192) -> LTR | N25: 8.952 | O25: 8.057 | P25: 0.51 | Q25: 12.24 | R25: 15.6 | W25: 33012991 | X25: 0
H26: 22021000 | I26: BE | J26: 24 | K26: 1 | L26: 24 | M26: =LOOKUP(H26,$W$4:$W$192,Séparer!$X$4:$X$192) -> LTR | N26: 13.104 | O26: 11.794 | P26: 0.695 | Q26: 16.68 | R26: 29.76 | W26: 33021010 | X26: 0
H27: 23091090 | I27: FR | J27: 1 | K27: 5 | L27: 5 | M27: =LOOKUP(H27,$W$4:$W$192,Séparer!$X$4:$X$192) -> 0 | N27: 0.58 | O27: 0.522 | P27: 0.756 | Q27: 3.78 | R27: 8.45 | W27: 33030010 | X27: 0
H28: 23099096 | I28: HU | J28: 11 | K28: 5 | L28: 14 | M28: =LOOKUP(H28,$W$4:$W$192,Séparer!$X$4:$X$192) -> 0 | N28: 7.58 | O28: 6.822 | P28: 5.978 | Q28: 26.18 | R28: 18.16 | W28: 33030090 | X28: 0
H29: 23099096 | I29: BE | J29: 2 | K29: 5 | L29: 9 | M29: =LOOKUP(H29,$W$4:$W$192,Séparer!$X$4:$X$192) -> 0 | N29: 23.724 | O29: 21.351 | P29: 7.84 | Q29: 43.68 | R29: 20.78 | W29: 33043000 | X29: 0
H30: 28363000 | I30: BE | J30: 7 | K30: 4 | L30: 9 | M30: =LOOKUP(H30,$W$4:$W$192,Séparer!$X$4:$X$192) -> 0 | N30: 6.756 | O30: 6.08 | P30: 2.948 | Q30: 11.517 | R30: 21.27 | W30: 33049900 | X30: 0
H31: 30051000 | I31: ES | J31: 1 | K31: 4 | L31: 4 | M31: =LOOKUP(H31,$W$4:$W$192,Séparer!$X$4:$X$192) -> 0 | N31: 0.104 | O31: 0.094 | P31: 0.269 | Q31: 1.076 | R31: 8.72 | W31: 33051000 | X31: 0
... H41: 33049900 | I41: CN | J41: 4 | K41: 200 | L41: 200 | M41: =LOOKUP(H41,$W$4:$W$192,Séparer!$X$4:$X$192) -> 0 | N41: 27.84 | O41: 25.056 | P41: 0.692 | Q41: 34.76 | R41: 192 | W41: 39232100 | X41: 0
H42: 33051000 | I42: FR | J42: 2 | K42: 4 | L42: 4 | M42: =LOOKUP(H42,$W$4:$W$192,Séparer!$X$4:$X$192) -> 0 | N42: 4.658 | O42: 4.192 | P42: 4.355 | Q42: 8.71 | R42: 7.9 | W42: 39233010 | X42: NAR
H43: 33059000 | I43: FR | J43: 1 | K43: 2 | L43: 2 | M43: =LOOKUP(H43,$W$4:$W$192,Séparer!$X$4:$X$192) -> 0 | N43: 1.136 | O43: 1.022 | P43: 0.96 | Q43: 1.92 | R43: 4.64 | W43: 39241000 | X43: 0
H44: 33073000 | I44: CN | J44: 12 | K44: 2 | L44: 12 | M44: =LOOKUP(H44,$W$4:$W$192,Séparer!$X$4:$X$192) -> 0 | N44: 0.24 | O44: 0.216 | P44: 3.5 | Q44: 21 | R44: 79.8 | W44: 39249000 | X44: 0
H45: 33074900 | I45: CN | J45: 2 | K45: 5 | L45: 5 | M45: =LOOKUP(H45,$W$4:$W$192,Séparer!$X$4:$X$192) -> 0 | N45: 1.24 | O45: 1.116 | P45: 4.977 | Q45: 7.812 | R45: 9.63 | W45: 39261000 | X45: 0
H46: 33079000 | I46: FR | J46: 2 | K46: 6 | L46: 6 | M46: =LOOKUP(H46,$W$4:$W$192,Séparer!$X$4:$X$192) -> 0 | N46: 1.46 | O46: 1.314 | P46: 0.876 | Q46: 2.674 | R46: 23.08 | W46: 39262000 | X46: 0
H47: 34011900 | I47: SY | J47: 1 | K47: 2 | L47: 2 | M47: =LOOKUP(H47,$W$4:$W$192,Séparer!$X$4:$X$192) -> 0 | N47: 2.306 | O47: 2.075 | P47: 4.333 | Q47: 8.666 | R47: 20.04 | W47: 39264000 | X47: 0
H48: 34013000 | I48: FR | J48: 1 | K48: 2 | L48: 2 | M48: =LOOKUP(H48,$W$4:$W$192,Séparer!$X$4:$X$192) -> 0 | N48: 2.36 | O48: 2.124 | P48: 2.08 | Q48: 4.16 | R48: 3.96 | W48: 39269097 | X48: 0
H49: 34013000 | I49: ES | J49: 1 | K49: 3 | L49: 3 | M49: =LOOKUP(H49,$W$4:$W$192,Séparer!$X$4:$X$192) -> 0 | N49: 1.764 | O49: 1.587 | P49: 1.155 | Q49: 3.465 | R49: 2.55 | W49: 40169200 | X49: 0
H50: 34025090 | I50: FR | J50: 19 | K50: 5 | L50: 20 | M50: =LOOKUP(H50,$W$4:$W$192,Séparer!$X$4:$X$192) -> 0 | N50: 19.738 | O50: 17.764 | P50: 10.35 | Q50: 49.928 | R50: 31.38 | W50: 42010000 | X50: 0
H51: 34025090 | I51: PL | J51: 10 | K51: 1 | L51: 10 | M51: =LOOKUP(H51,$W$4:$W$192,Séparer!$X$4:$X$192) -> 0 | N51: 0.86 | O51: 0.774 | P51: 1.2 | Q51: 12 | R51: 18.3 | W51: 42022100 | X51: Nar
H52: 34025090 | I52: IT | J52: 24 | K52: 2 | L52: 24 | M52: =LOOKUP(H52,$W$4:$W$192,Séparer!$X$4:$X$192) -> 0 | N52: 21.996 | O52: 19.796 | P52: 4.6 | Q52: 55.2 | R52: 31.2 | W52: 44013100 | X52: 0
H53: 34060000 | I53: BE | J53: 13 | K53: 11 | L53: 20 | M53: =LOOKUP(H53,$W$4:$W$192,Séparer!$X$4:$X$192) -> 0 | N53: 18.06 | O53: 16.255 | P53: 7.949 | Q53: 49.434 | R53: 52.78 | W53: 44191900 | X53: 0
H54: 34060000 | I54: IN | J54: 2 | K54: 3 | L54: 6 | M54: =LOOKUP(H54,$W$4:$W$192,Séparer!$X$4:$X$192) -> 0 | N54: 6.423 | O54: 5.781 | P54: 4.732 | Q54: 14.196 | R54: 30.25 | W54: 44209010 | X54: MTQ
H55: 34060000 | I55: CN | J55: 1 | K55: 3 | L55: 3 | M55: =LOOKUP(H55,$W$4:$W$192,Séparer!$X$4:$X$192) -> 0 | N55: 2.334 | O55: 2.101 | P55: 2.004 | Q55: 6.012 | R55: 10.65 | W55: 44211000 | X55: NAR
H56: 34060000 | I56: PL | J56: 1 | K56: 2 | L56: 2 | M56: =LOOKUP(H56,$W$4:$W$192,Séparer!$X$4:$X$192) -> 0 | N56: 1.732 | O56: 1.559 | P56: 1.41 | Q56: 2.82 | R56: 4.8 | W56: 44219100 | X56: 0
H57: 38249996 | I57: DE | J57: 1 | K57: 8 | L57: 8 | M57: =LOOKUP(H57,$W$4:$W$192,Séparer!$X$4:$X$192) -> 0 | N57: 35.2 | O57: 31.68 | P57: 12 | Q57: 96 | R57: 26.8 | W57: 48030090 | X57: 0
H58: 39232100 | I58: FR | J58: 25 | K58: 3 | L58: 75 | M58: =LOOKUP(H58,$W$4:$W$192,Séparer!$X$4:$X$192) -> 0 | N58: 25.125 | O58: 22.613 | P58: 3 | Q58: 225 | R58: 91.5 | W58: 48102200 | X58: 0
H59: 39233010 | I59: CN | J59: 1 | K59: 3 | L59: 3 | M59: =LOOKUP(H59,$W$4:$W$192,Séparer!$X$4:$X$192) -> NAR | N59: 0.225 | O59: 0.203 | P59: 1.127 | Q59: 3.381 | R59: 3.09 | W59: 48114900 | X59: 0
H60: 39241000 | I60: CN | J60: 42 | K60: 26 | L60: 59 | M60: =LOOKUP(H60,$W$4:$W$192,Séparer!$X$4:$X$192) -> 0 | N60: 7.514 | O60: 6.761 | P60: 11.768 | Q60: 50.216 | R60: 81.05 | W60: 48119000 | X60: 0
H61: 39241000 | I61: BE | J61: 1 | K61: 3 | L61: 3 | M61: =LOOKUP(H61,$W$4:$W$192,Séparer!$X$4:$X$192) -> 0 | N61: 0.84 | O61: 0.756 | P61: 3.645 | Q61: 10.935 | R61: 11.1 | W61: 48131000 | X61: 0
H62: 39249000 | I62: PL | J62: 1 | K62: 3 | L62: 3 | M62: =LOOKUP(H62,$W$4:$W$192,Séparer!$X$4:$X$192) -> 0 | N62: 0.759 | O62: 0.683 | P62: 3.523 | Q62: 10.569 | R62: 5.37 | W62: 48171000 | X62: 0
H63: 39249000 | I63: FR | J63: 1 | K63: 2 | L63: 2 | M63: =LOOKUP(H63,$W$4:$W$192,Séparer!$X$4:$X$192) -> 0 | N63: 5.32 | O63: 4.788 | P63: 71.424 | Q63: 142.848 | R63: 19.7 | W63: 48182010 | X63: 0
H64: 39249000 | I64: CN | J64: 12 | K64: 1 | L64: 12 | M64: =LOOKUP(H64,$W$4:$W$192,Séparer!$X$4:$X$192) -> 0 | N64: 0.54 | O64: 0.486 | P64: 0.735 | Q64: 8.82 | R64: 11.16 | W64: 48191000 | X64: 0
H65: 39261000 | I65: IT | J65: 1 | K65: 3 | L65: 3 | M65: =LOOKUP(H65,$W$4:$W$192,Séparer!$X$4:$X$192) -> 0 | N65: 0.273 | O65: 0.246 | P65: 1 | Q65: 3 | R65: 2.67 | W65: 48201030 | X65: 0
H66: 39262000 | I66: CN | J66: 12 | K66: 7 | L66: 14 | M66: =LOOKUP(H66,$W$4:$W$192,Séparer!$X$4:$X$192) -> 0 | N66: 0.818 | O66: 0.737 | P66: 1.442 | Q66: 2.904 | R66: 12.8 | W66: 48211010 | X66: 0
H67: 39264000 | I67: CN | J67: 25 | K67: 15 | L67: 39 | M67: =LOOKUP(H67,$W$4:$W$192,Séparer!$X$4:$X$192) -> 0 | N67: 49.94 | O67: 44.946 | P67: 123.391 | Q67: 413.062 | R67: 397.61 | W67: 48219010 | X67: 0
... H73: 42010000 | I73: CN | J73: 1 | K73: 2 | L73: 2 | M73: =LOOKUP(H73,$W$4:$W$192,Séparer!$X$4:$X$192) -> 0 | N73: 0.276 | O73: 0.248 | P73: 0.83 | Q73: 1.66 | R73: 3.74 | W73: 56075011 | X73: 0
H74: 42022100 | I74: CN | J74: 12 | K74: 2 | L74: 12 | M74: =LOOKUP(H74,$W$4:$W$192,Séparer!$X$4:$X$192) -> Nar | N74: 4.08 | O74: 3.672 | P74: 1.548 | Q74: 9.288 | R74: 93.12 | W74: 57049000 | X74: MTK
H75: 42022100 | I75: VN | J75: 24 | K75: 6 | L75: 24 | M75: =LOOKUP(H75,$W$4:$W$192,Séparer!$X$4:$X$192) -> Nar | N75: 10.8 | O75: 9.72 | P75: 23.232 | Q75: 92.928 | R75: 383.52 | W75: 57050030 | X75: MTK
H76: 44013100 | I76: TR | J76: 1 | K76: 2 | L76: 2 | M76: =LOOKUP(H76,$W$4:$W$192,Séparer!$X$4:$X$192) -> 0 | N76: 13.08 | O76: 11.772 | P76: 8 | Q76: 16 | R76: 3.06 | W76: 61031090 | X76: NAR
H77: 44191900 | I77: CN | J77: 2 | K77: 2 | L77: 2 | M77: =LOOKUP(H77,$W$4:$W$192,Séparer!$X$4:$X$192) -> 0 | N77: 1.22 | O77: 1.099 | P77: 14.34 | Q77: 14.34 | R77: 7.86 | W77: 61032200 | X77: NAR
H78: 44209010 | I78: CN | J78: 2 | K78: 12 | L78: 12 | M78: =LOOKUP(H78,$W$4:$W$192,Séparer!$X$4:$X$192) -> MTQ | N78: 3 | O78: 2.7 | P78: 1.87 | Q78: 11.22 | R78: 58.56 | W78: 61032300 | X78: NAR
H79: 44211000 | I79: CN | J79: 18 | K79: 1 | L79: 18 | M79: =LOOKUP(H79,$W$4:$W$192,Séparer!$X$4:$X$192) -> NAR | N79: 9.486 | O79: 8.537 | P79: 3.744 | Q79: 67.392 | R79: 35.82 | W79: 61034900 | X79: NAR
H80: 44219100 | I80: CN | J80: 2 | K80: 3 | L80: 3 | M80: =LOOKUP(H80,$W$4:$W$192,Séparer!$X$4:$X$192) -> 0 | N80: 2.514 | O80: 2.262 | P80: 10.752 | Q80: 16.128 | R80: 14.46 | W80: 61042300 | X80: NAR
H81: 48030090 | I81: NL | J81: 1 | K81: 6 | L81: 6 | M81: =LOOKUP(H81,$W$4:$W$192,Séparer!$X$4:$X$192) -> 0 | N81: 0.33 | O81: 0.297 | P81: 0.545 | Q81: 3.27 | R81: 3.54 | W81: 61044300 | X81: NAR
H82: 48102200 | I82: NL | J82: 122 | K82: 4 | L82: 122 | M82: =LOOKUP(H82,$W$4:$W$192,Séparer!$X$4:$X$192) -> 0 | N82: 33.514 | O82: 30.164 | P82: 8.674 | Q82: 200.032 | R82: 96.72 | W82: 61046200 | X82: NAR
H83: 48114900 | I83: NL | J83: 72 | K83: 2 | L83: 72 | M83: =LOOKUP(H83,$W$4:$W$192,Séparer!$X$4:$X$192) -> 0 | N83: 7.992 | O83: 7.192 | P83: 2.64 | Q83: 95.04 | R83: 54.72 | W83: 61046300 | X83: NAR
H84: 48119000 | I84: CN | J84: 410 | K84: 8 | L84: 410 | M84: =LOOKUP(H84,$W$4:$W$192,Séparer!$X$4:$X$192) -> 0 | N84: 47.8 | O84: 43.02 | P84: 10.394 | Q84: 483.99 | R84: 209.5 | W84: 61046900 | X84: NAR
H85: 48119000 | I85: DE | J85: 20 | K85: 2 | L85: 20 | M85: =LOOKUP(H85,$W$4:$W$192,Séparer!$X$4:$X$192) -> 0 | N85: 3.32 | O85: 2.988 | P85: 1.2 | Q85: 12 | R85: 6 | W85: 61051000 | X85: NAR
... H95: 55111000 | I95: TR | J95: 10 | K95: 1 | L95: 10 | M95: =LOOKUP(H95,$W$4:$W$192,Séparer!$X$4:$X$192) -> 0 | N95: 0.59 | O95: 0.531 | P95: 0.66 | Q95: 6.6 | R95: 13.4 | W95: 61109090 | X95: Nar
H96: 56012290 | I96: DE | J96: 21 | K96: 1 | L96: 21 | M96: =LOOKUP(H96,$W$4:$W$192,Séparer!$X$4:$X$192) -> 0 | N96: 0.924 | O96: 0.832 | P96: 0.843 | Q96: 17.703 | R96: 8.19 | W96: 61142000 | X96: 0
H97: 56012290 | I97: FR | J97: 24 | K97: 1 | L97: 24 | M97: =LOOKUP(H97,$W$4:$W$192,Séparer!$X$4:$X$192) -> 0 | N97: 2.04 | O97: 1.836 | P97: 0.595 | Q97: 14.28 | R97: 7.2 | W97: 61152100 | X97: Nar
H98: 56060010 | I98: CN | J98: 12 | K98: 15 | L98: 42 | M98: =LOOKUP(H98,$W$4:$W$192,Séparer!$X$4:$X$192) -> 0 | N98: 2.452 | O98: 2.207 | P98: 2.038 | Q98: 28.984 | R98: 56.28 | W98: 61152200 | X98: Nar
H99: 56075011 | I99: CN | J99: 1 | K99: 3 | L99: 3 | M99: =LOOKUP(H99,$W$4:$W$192,Séparer!$X$4:$X$192) -> 0 | N99: 0.51 | O99: 0.459 | P99: 1.127 | Q99: 3.381 | R99: 4.41 | W99: 61152900 | X99: Nar
H100: 57049000 | I100: CN | J100: 1 | K100: 2 | L100: 2 | M100: =LOOKUP(H100,$W$4:$W$192,Séparer!$X$4:$X$192) -> MTK | N100: 1.796 | O100: 1.616 | P100: 3.64 | Q100: 7.28 | R100: 5.1 | W100: 61153011 | X100: NPR
H101: 57050030 | I101: CN | J101: 1 | K101: 2 | L101: 2 | M101: =LOOKUP(H101,$W$4:$W$192,Séparer!$X$4:$X$192) -> MTK | N101: 0.746 | O101: 0.671 | P101: 3.049 | Q101: 6.098 | R101: 4.04 | W101: 61153019 | X101: NPR
H102: 61031090 | I102: BD | J102: 2 | K102: 2 | L102: 2 | M102: =LOOKUP(H102,$W$4:$W$192,Séparer!$X$4:$X$192) -> NAR | N102: 0.674 | O102: 0.606 | P102: 3.284 | Q102: 3.284 | R102: 8.47 | W102: 61153090 | X102: NPR
H103: 61032200 | I103: PK | J103: 1 | K103: 2 | L103: 2 | M103: =LOOKUP(H103,$W$4:$W$192,Séparer!$X$4:$X$192) -> NAR | N103: 0.72 | O103: 0.648 | P103: 3.2 | Q103: 6.4 | R103: 8.42 | W103: 61159500 | X103: NPR
H104: 61032300 | I104: CN | J104: 12 | K104: 4 | L104: 12 | M104: =LOOKUP(H104,$W$4:$W$192,Séparer!$X$4:$X$192) -> NAR | N104: 4.338 | O104: 3.904 | P104: 8.58 | Q104: 25.74 | R104: 38.16 | W104: 62033990 | X104: NAR
H105: 61034900 | I105: IN | J105: 3 | K105: 3 | L105: 3 | M105: =LOOKUP(H105,$W$4:$W$192,Séparer!$X$4:$X$192) -> NAR | N105: 0.816 | O105: 0.734 | P105: 5.76 | Q105: 5.76 | R105: 8.13 | W105: 62034231 | X105: NAR
H106: 61042300 | I106: CN | J106: 6 | K106: 2 | L106: 6 | M106: =LOOKUP(H106,$W$4:$W$192,Séparer!$X$4:$X$192) -> NAR | N106: 1.596 | O106: 1.436 | P106: 3.57 | Q106: 10.71 | R106: 29.34 | W106: 62044300 | X106: NAR
H107: 61044300 | I107: IN | J107: 12 | K107: 2 | L107: 12 | M107: =LOOKUP(H107,$W$4:$W$192,Séparer!$X$4:$X$192) -> NAR | N107: 2.904 | O107: 2.614 | P107: 4 | Q107: 24 | R107: 55.68 | W107: 62044990 | X107: NAR
H108: 61044300 | I108: FR | J108: 12 | K108: 2 | L108: 12 | M108: =LOOKUP(H108,$W$4:$W$192,Séparer!$X$4:$X$192) -> NAR | N108: 2.628 | O108: 2.366 | P108: 3.276 | Q108: 19.656 | R108: 83.4 | W108: 62045990 | X108: NAR
... H113: 61071100 | I113: CN | J113: 1 | K113: 3 | L113: 3 | M113: =LOOKUP(H113,$W$4:$W$192,Séparer!$X$4:$X$192) -> NAR | N113: 0.552 | O113: 0.497 | P113: 1.344 | Q113: 4.032 | R113: 5.64 | W113: 62069090 | X113: NAR
H114: 61082100 | I114: CN | J114: 18 | K114: 6 | L114: 20 | M114: =LOOKUP(H114,$W$4:$W$192,Séparer!$X$4:$X$192) -> NAR | N114: 1.607 | O114: 1.447 | P114: 2.848 | Q114: 12.637 | R114: 33.75 | W114: 62114390 | X114: 0
H115: 61082200 | I115: CN | J115: 18 | K115: 6 | L115: 20 | M115: =LOOKUP(H115,$W$4:$W$192,Séparer!$X$4:$X$192) -> NAR | N115: 1.705 | O115: 1.533 | P115: 0.833 | Q115: 1.531 | R115: 53.33 | W115: 62121010 | X115: NAR
H116: 61089200 | I116: CN | J116: 6 | K116: 3 | L116: 6 | M116: =LOOKUP(H116,$W$4:$W$192,Séparer!$X$4:$X$192) -> NAR | N116: 0.462 | O116: 0.416 | P116: 1.797 | Q116: 3.594 | R116: 8.62 | W116: 62121090 | X116: NAR
H117: 61091000 | I117: IN | J117: 52 | K117: 11 | L117: 58 | M117: =LOOKUP(H117,$W$4:$W$192,Séparer!$X$4:$X$192) -> NAR | N117: 10.234 | O117: 9.21 | P117: 15.041 | Q117: 98.02 | R117: 207.82 | W117: 62143000 | X117: NAR
H118: 61091000 | I118: CN | J118: 5 | K118: 1 | L118: 5 | M118: =LOOKUP(H118,$W$4:$W$192,Séparer!$X$4:$X$192) -> NAR | N118: 0.635 | O118: 0.572 | P118: 0.5 | Q118: 2.5 | R118: 5.5 | W118: 63014090 | X118: NAR
H119: 61101910 | I119: PK | J119: 26 | K119: 6 | L119: 26 | M119: =LOOKUP(H119,$W$4:$W$192,Séparer!$X$4:$X$192) -> NAR | N119: 10.517 | O119: 9.465 | P119: 14.809 | Q119: 48.539 | R119: 158.05 | W119: 63022100 | X119: 0
H120: 61101910 | I120: BD | J120: 19 | K120: 9 | L120: 24 | M120: =LOOKUP(H120,$W$4:$W$192,Séparer!$X$4:$X$192) -> NAR | N120: 9.24 | O120: 8.316 | P120: 5.41 | Q120: 32.46 | R120: 136.56 | W120: 63022290 | X120: 0
H121: 61101910 | I121: IN | J121: 56 | K121: 2 | L121: 56 | M121: =LOOKUP(H121,$W$4:$W$192,Séparer!$X$4:$X$192) -> NAR | N121: 34.776 | O121: 31.298 | P121: 9.3 | Q121: 260.4 | R121: 414.96 | W121: 63023100 | X121: 0
H122: 61101990 | I122: PK | J122: 2 | K122: 1 | L122: 2 | M122: =LOOKUP(H122,$W$4:$W$192,Séparer!$X$4:$X$192) -> NAR | N122: 0.86 | O122: 0.774 | P122: 3.52 | Q122: 7.04 | R122: 9.54 | W122: 63029390 | X122: 0
H123: 61102091 | I123: BD | J123: 24 | K123: 4 | L123: 24 | M123: =LOOKUP(H123,$W$4:$W$192,Séparer!$X$4:$X$192) -> Nar | N123: 6.708 | O123: 6.038 | P123: 9.842 | Q123: 59.052 | R123: 171.84 | W123: 63039290 | X123: MTK
H124: 61103010 | I124: CN | J124: 13 | K124: 3 | L124: 13 | M124: =LOOKUP(H124,$W$4:$W$192,Séparer!$X$4:$X$192) -> Nar | N124: 3.146 | O124: 2.831 | P124: 8.442 | Q124: 34.152 | R124: 76.52 | W124: 63041990 | X124: NAR
H125: 61109090 | I125: BD | J125: 56 | K125: 18 | L125: 60 | M125: =LOOKUP(H125,$W$4:$W$192,Séparer!$X$4:$X$192) -> Nar | N125: 16.601 | O125: 14.941 | P125: 41.609 | Q125: 160.584 | R125: 306.57 | W125: 63049300 | X125: 0
H126: 61109090 | I126: PK | J126: 24 | K126: 4 | L126: 24 | M126: =LOOKUP(H126,$W$4:$W$192,Séparer!$X$4:$X$192) -> Nar | N126: 7.884 | O126: 7.096 | P126: 11.332 | Q126: 67.992 | R126: 103.92 | W126: 63071010 | X126: 0
H127: 61142000 | I127: IN | J127: 2 | K127: 1 | L127: 2 | M127: =LOOKUP(H127,$W$4:$W$192,Séparer!$X$4:$X$192) -> 0 | N127: 0.352 | O127: 0.317 | P127: 1.176 | Q127: 2.352 | R127: 5.1 | W127: 63071030 | X127: 0
...

Sheet Valeur Additionelle
D3: NBR | E3: Code | F3: Valeur/Unité
D6: 1 | E6: 04015011 | F6: 0
D7: 2 | E7: 17049061 | F7: 0
D8: 3 | E8: 17049065 | F8: 0
D9: 4 | E9: 17049071 | F9: 0
D10: 5 | E10: 18063100 | F10: 0
D11: 6 | E11: 18069019 | F11: 0
D12: 7 | E12: 18069031 | F12: 0
D13: 8 | E13: 18069039 | F13: 0
D14: 9 | E14: 18069060 | F14: 0
D15: 10 | E15: 19053119 | F15: 0
D16: 11 | E16: 19053199 | F16: 0
D17: 12 | E17: 20052020 | F17: 0
D18: 13 | E18: 21069051 | F18: 0
D19: 14 | E19: 21069059 | F19: 0
D20: 15 | E20: 22011090 | F20: LTR | G20: Regarder description pour le litrage
D21: 16 | E21: 22021000 | F21: LTR | G21: Regarder description pour le litrage
D22: 17 | E22: 23091090 | F22: 0
D23: 18 | E23: 23099096 | F23: 0
D24: 19 | E24: 28363000 | F24: 0
D25: 20 | E25: 30051000 | F25: 0
D26: 21 | E26: 33012949 | F26: 0
D27: 22 | E27: 33012991 | F27: 0
D28: 23 | E28: 33021010 | F28: 0
D29: 24 | E29: 33030010 | F29: 0
D30: 25 | E30: 33030090 | F30: 0
D31: 26 | E31: 33043000 | F31: 0
D32: 27 | E32: 33049900 | F32: 0
D33: 28 | E33: 33051000 | F33: 0
... D43: 38 | E43: 39232100 | F43: 0
D44: 39 | E44: 39233010 | F44: NAR | G44: Nombre de pièces
D45: 40 | E45: 39241000 | F45: 0
D46: 41 | E46: 39249000 | F46: 0
D47: 42 | E47: 39261000 | F47: 0
D48: 43 | E48: 39262000 | F48: 0
D49: 44 | E49: 39264000 | F49: 0
D50: 45 | E50: 39269097 | F50: 0
D51: 46 | E51: 40169200 | F51: 0
C52: 0.25 | D52: 47 | E52: 42010000 | F52: 0
D53: 48 | E53: 42022100 | F53: Nar | G53: Nombre de pièces
D54: 49 | E54: 44013100 | F54: 0
D55: 50 | E55: 44191900 | F55: 0
D56: 51 | E56: 44209010 | F56: MTQ | G56: Mètre cube
D57: 52 | E57: 44211000 | F57: NAR | G57: Nombre de pièces
D58: 53 | E58: 44219100 | F58: 0
D59: 54 | E59: 48030090 | F59: 0
D60: 55 | E60: 48102200 | F60: 0
D61: 56 | E61: 48114900 | F61: 0
D62: 57 | E62: 48119000 | F62: 0
D63: 58 | E63: 48131000 | F63: 0
D64: 59 | E64: 48171000 | F64: 0
D65: 60 | E65: 48182010 | F65: 0
D66: 61 | E66: 48191000 | F66: 0
D67: 62 | E67: 48201030 | F67: 0
D68: 63 | E68: 48211010 | F68: 0
D69: 64 | E69: 48219010 | F69: 0
... D75: 70 | E75: 56075011 | F75: 0
D76: 71 | E76: 57049000 | F76: MTK | G76: Mètre carré
D77: 72 | E77: 57050030 | F77: MTK | G77: Mètre carré
D78: 73 | E78: 61031090 | F78: NAR | G78: Nombre de pièces
D79: 74 | E79: 61032200 | F79: NAR | G79: Nombre de pièces
D80: 75 | E80: 61032300 | F80: NAR | G80: Nombre de pièces
D81: 76 | E81: 61034900 | F81: NAR | G81: Nombre de pièces
D82: 77 | E82: 61042300 | F82: NAR | G82: Nombre de pièces
D83: 78 | E83: 61044300 | F83: NAR | G83: Nombre de pièces
D84: 79 | E84: 61046200 | F84: NAR | G84: Nombre de pièces
D85: 80 | E85: 61046300 | F85: NAR | G85: Nombre de pièces
D86: 81 | E86: 61046900 | F86: NAR | G86: Nombre de pièces
D87: 82 | E87: 61051000 | F87: NAR | G87: Nombre de pièces
... D97: 92 | E97: 61109090 | F97: Nar | G97: Nombre de pièces
D98: 93 | E98: 61142000 | F98: 0
C99: 0.5 | D99: 94 | E99: 61152100 | F99: Nar | G99: Nombre de pièces
D100: 95 | E100: 61152200 | F100: Nar | G100: Nombre de pièces
D101: 96 | E101: 61152900 | F101: Nar | G101: Nombre de pièces
D102: 97 | E102: 61153011 | F102: NPR | G102: Nombre de paires
D103: 98 | E103: 61153019 | F103: NPR | G103: Nombre de paires
D104: 99 | E104: 61153090 | F104: NPR | G104: Nombre de paires
D105: 100 | E105: 61159500 | F105: NPR | G105: Nombre de paires
D106: 101 | E106: 62033990 | F106: NAR | G106: Nombre de pièces
D107: 102 | E107: 62034231 | F107: NAR | G107: Nombre de pièces
D108: 103 | E108: 62044300 | F108: NAR | G108: Nombre de pièces
D109: 104 | E109: 62044990 | F109: NAR | G109: Nombre de pièces
D110: 105 | E110: 62045990 | F110: NAR | G110: Nombre de pièces
D111: 106 | E111: 62046290 | F111: NAR | G111: Nombre de pièces
... D115: 110 | E115: 62069090 | F115: NAR | G115: Nombre de pièces
D116: 111 | E116: 62114390 | F116: 0
D117: 112 | E117: 62121010 | F117: NAR | G117: Nombre de pièces
D118: 113 | E118: 62121090 | F118: NAR | G118: Nombre de pièces
D119: 114 | E119: 62143000 | F119: NAR | G119: Nombre de pièces
D120: 115 | E120: 63014090 | F120: NAR | G120: Nombre de pièces
D121: 116 | E121: 63022100 | F121: 0
D122: 117 | E122: 63022290 | F122: 0
D123: 118 | E123: 63023100 | F123: 0
D124: 119 | E124: 63029390 | F124: 0
D125: 120 | E125: 63039290 | F125: MTK | G125: Mètre carré
D126: 121 | E126: 63041990 | F126: NAR | G126: Nombre de pièces
D127: 122 | E127: 63049300 | F127: 0
D128: 123 | E128: 63071010 | F128: 0
D129: 124 | E129: 63071030 | F129: 0
D130: 125 | E130: 63079010 | F130: 0
...

Sheet ETAPE
A4: Nouvel onglet | B4: 1 | C4: Copier les données brutes dans un seul fichier. NE PAS PRENDRE LES PALETTES
B5: 2 | C5: Vérifier si le total des données brutes = total des factures ( vérification par les totaux)
B6: 3 | C6: Supprimer les colonnes vides et inutiles
A7: Nouvel onglet | B7: 4 | C7: Combiner les codes et les origines avec la formule concaténer
C8: Faire une colonne avec la formule et une colonne avec la valeur obtenue
B9: 5 | C9: Supprimer les colonnes codes, origine et formule conca
B10: 6 | C10: Réduire les codes dans onglet données et consolider
C11: Référence = tableau Choisir case vide pour que le tableau se calcule (a coté)
A12: Nouvel onglet | B12: 7 | C12: Séparer de les codes et les origines
C13: Créer une colone vide pour code ou origine
C14: Utiliser fonction convertir dans onglet données
C15: Sélectionner l'ensemble des cellules à séparer puis utiliser fonction
B16: 8 | C16: Copier les données obtenues du tableau final dans le fichier infection ( pas sur le vierge !)
C17: Attention au valeur additionelle - s'adapter
C18: Faire une colonne pour la valeur additionelle et utiliser formule recherche ( Attention, peut-être pas assez fiable)
C19: Pour les valeurs autre que Nar ET NPP, prendre le volume total

Sheet Trafic - Résumé 
B1: Code Nomenclature | C1: Origine | D1: Devise | E1: Colisage | F1: Poids Brut | G1: Poids Net | H1: Valeur | I1: Valeur douane | J1: TVA | K1: N° Facture
A2: 1 | B2: ='[1]INTEGRA - Détails'!B3 -> 0 | C2: ='[1]INTEGRA - Détails'!B4 -> 0 | D2: =LOOKUP(K2,$H$17:$H$25,$K$17:$K$25) -> #N/A | F2: 2626.257 | G2: 2363.631 | H2: 24618.77
A3: 2 | B3: ='[1]INTEGRA - Détails'!D3 -> 0 | C3: ='[1]INTEGRA - Détails'!D4 -> 0 | D3: =LOOKUP(K3,$H$17:$H$25,$K$17:$K$25) -> #N/A | F3: 510
A4: 3 | B4: ='[1]INTEGRA - Détails'!F3 -> 0 | C4: ='[1]INTEGRA - Détails'!F4 -> 0 | D4: =LOOKUP(K4,$H$17:$H$25,$K$17:$K$25) -> #N/A
A5: 4 | B5: ='[1]INTEGRA - Détails'!H3 -> 0 | C5: ='[1]INTEGRA - Détails'!H4 -> 0 | D5: =LOOKUP(K5,$H$17:$H$25,$K$17:$K$25) -> #N/A
A6: 5 | B6: ='[1]INTEGRA - Détails'!J3 -> 0 | C6: ='[1]INTEGRA - Détails'!J4 -> 0 | D6: =LOOKUP(K6,$H$17:$H$25,$K$17:$K$25) -> #N/A
A7: 6 | B7: ='[1]INTEGRA - Détails'!L3 -> 0 | C7: ='[1]INTEGRA - Détails'!L4 -> 0 | D7: =LOOKUP(K7,$H$17:$H$25,$K$17:$K$25) -> #N/A
A8: 7 | B8: ='[1]INTEGRA - Détails'!N3 -> 0 | C8: ='[1]INTEGRA - Détails'!N4 -> 0 | D8: =LOOKUP(K8,$H$17:$H$25,$K$17:$K$25) -> #N/A
A9: 8 | B9: ='[1]INTEGRA - Détails'!P3 -> 0 | C9: ='[1]INTEGRA - Détails'!P4 -> 0 | D9: =LOOKUP(K9,$H$17:$H$25,$K$17:$K$25) -> #N/A
A10: 9 | B10: ='[1]INTEGRA - Détails'!R3 -> 0 | C10: ='[1]INTEGRA - Détails'!R4 -> 0 | D10: =LOOKUP(K10,$H$17:$H$25,$K$17:$K$25) -> #N/A
A11: 10 | B11: ='[1]INTEGRA - Détails'!T3 -> 0 | C11: ='[1]INTEGRA - Détails'!T4 -> 0 | D11: =LOOKUP(K11,$H$17:$H$25,$K$17:$K$25) -> #N/A
B13: TOTAL | E13: =SUM(E2:E12) -> 0 | F13: =SUM(F2:F12) -> 3136.257 | G13: =SUM(G2:G12) -> 2363.631 | H13: =SUM(H2:H11) -> 24618.77 | I13: =SUM(I2:I11) -> 0 | J13: =SUM(J2:J11) -> 0
B14: Total Colis | D14: =C14-E13 -> 0
B15: Poids Brut | C15: =455.518+1036.537+1134.202+68+221+221 -> 3136.257 | D15: =IF($F$13=$C$15,"OK","ERREUR") -> OK
B16: Poids à rajouter s/ last rubrique : | C16: =C15-F13 -> 0 | H16: N° Facture | I16: Valeur | J16: P. NET | K16: Devise
B17: Poids Net MRN | C17: =409.977+932.877+1020.777 -> 2363.631 | D17: =IF($G$13=$C$17,"OK","ERREUR") -> OK | E17: =C17-G13 -> 0 | H17: 90128373 | I17: 2922.32 | J17: 409.977
B18: N° Rubrique | C18: =COUNT(B2:B11) -> 10 | H18: 90128374 | I18: 10694.7 | J18: 932.877
B19: Valeur douane | C19: =LOOKUP(C18,B36:B55,C36:C55) -> 0 | H19: 90128376 | I19: 11001.75 | J19: 1020.777
B20: Changement TVA | C20: =LOOKUP(C18,B36:B55,E36:E55) -> 5
H26: Total | I26: =SUM(I17:I25) -> 24618.77 | J26: =SUM(J17:J25) -> 2363.631
I27: =IF(H13=I26,"OK","ERREUR") -> OK | J27: =IF(G13=J26,"OK","ERREUR") -> OK
I28: =I26-H13 -> 0 | J28: =J26-G13 -> 0
B34: SANS DROITS DE DOUANE
B35: Nombre de rubrique | C35: Valeur douane | E35: TVA | H35: Valeur douane | J35: TVA
B36: 1 | C36: 0 | E36: =50/B36 -> 50 | G36: 1 | H36: -400 | J36: 450
B37: 2 | C37: 0 | E37: =50/B37 -> 25 | G37: 2 | H37: -200 | J37: 225
B38: 3 | C38: 0 | E38: 10+20+20 | G38: 3 | H38: -150&-150&-100 | J38: 150
B39: 4 | C39: 0 | E39: =50/B39 -> 12.5 | G39: 4 | H39: -100 | J39: 3*100&150
B40: 5 | C40: 0 | E40: =50/B40 -> 10 | G40: 5 | H40: -80 | J40: 90
B41: 6 | C41: 0 | E41: 5*8+10 | G41: 6 | H41: 5*-60&-100 | J41: 75
B42: 7 | C42: 0 | E42: 6*7+8 | G42: 7 | H42: 6*-50&-100 | J42: 6*50&150
B43: 8 | C43: 0 | E43: =50/B43 -> 6.25 | G43: 8 | H43: -50 | J43: 7*50&100
B44: 9 | C44: 0 | E44: 8*5+10 | G44: 9 | H44: 8*-40&-80 | J44: 50
B45: 10 | C45: 0 | E45: =50/B45 -> 5 | G45: 10 | H45: -40 | J45: 45 | L45: =12*3 -> 36
B46: 11 | C46: 0 | E46: 10*4+10 | G46: 11 | H46: 10*-30 & -100 | J46: 10*40&50
B47: 12 | C47: 0 | E47: 11*4+6 | G47: 12 | H47: 11*-30 & -70 | J47: 11*30&120
B48: 13 | C48: 0 | E48: 12*3+14 | G48: 13 | H48: 12*-30 & -40 | J48: 12*30&90
B49: 14 | C49: 0 | E49: 13*3+11 | G49: 14 | H49: 13*-30 & -10 | J49: 13*30&60
B50: 15 | C50: 0 | E50: 14*3+8 | G50: 15 | H50: 14*-25 & -50 | J50: 30
B51: 16 | C51: 0 | E51: 15*3+5 | G51: 16 | H51: -25 | J51: 15*25 & 75
B52: 17 | C52: 0 | E52: 16*2+18 | G52: 17 | H52: 16*-20 & -80 | J52: 16*25 & 50
B53: 18 | C53: 0 | E53: 17*2+16 | G53: 18 | H53: 17*-20 & -60 | J53: 25
B54: 19 | C54: 0 | E54: 18*2+14 | G54: 19 | H54: 18*-20 & -40 | J54: 18*20 & 90
B55: 20 | C55: 0 | E55: =50/B55 -> 2.5 | G55: 20 | H55: -20 | J55: 19*20 & 70
